{
    "USC00010655": {
        "Lat": 34.6892, 
        "Lon": -86.8819, 
        "Marker": 1
    }, 
    "USC00011099": {
        "Lat": 34.9786, 
        "Lon": -85.8008, 
        "Marker": 1
    }, 
    "USC00011620": {
        "Lat": 33.285, 
        "Lon": -86.3431, 
        "Marker": 1
    }, 
    "USC00011803": {
        "Lat": 30.3875, 
        "Lon": -88.2269, 
        "Marker": 1
    }, 
    "USC00013573": {
        "Lat": 34.3344, 
        "Lon": -86.3297, 
        "Marker": 1
    }, 
    "USC00015635": {
        "Lat": 34.4883, 
        "Lon": -87.2989, 
        "Marker": 1
    }, 
    "USC00020080": {
        "Lat": 32.3697, 
        "Lon": -112.86, 
        "Marker": 1
    }, 
    "USC00020586": {
        "Lat": 34.5972, 
        "Lon": -113.1739, 
        "Marker": 4
    }, 
    "USC00020632": {
        "Lat": 33.8097, 
        "Lon": -111.6497, 
        "Marker": 4
    }, 
    "USC00020750": {
        "Lat": 36.6778, 
        "Lon": -110.5411, 
        "Marker": 2
    }, 
    "USC00020808": {
        "Lat": 33.4783, 
        "Lon": -109.7517, 
        "Marker": 2
    }, 
    "USC00021314": {
        "Lat": 32.9947, 
        "Lon": -111.5367, 
        "Marker": 1
    }, 
    "USC00021353": {
        "Lat": 33.9825, 
        "Lon": -112.3617, 
        "Marker": 2
    }, 
    "USC00021654": {
        "Lat": 34.7569, 
        "Lon": -112.4567, 
        "Marker": 2
    }, 
    "USC00022109": {
        "Lat": 34.305, 
        "Lon": -112.165, 
        "Marker": 2
    }, 
    "USC00023160": {
        "Lat": 35.2681, 
        "Lon": -111.7428, 
        "Marker": 3
    }, 
    "USC00023303": {
        "Lat": 35.7164, 
        "Lon": -109.5661, 
        "Marker": 5
    }, 
    "USC00023393": {
        "Lat": 32.9481, 
        "Lon": -112.7131, 
        "Marker": 2
    }, 
    "USC00023961": {
        "Lat": 34.3925, 
        "Lon": -110.5581, 
        "Marker": 2
    }, 
    "USC00024977": {
        "Lat": 33.4992, 
        "Lon": -112.3631, 
        "Marker": 1
    }, 
    "USC00025412": {
        "Lat": 34.1142, 
        "Lon": -109.8589, 
        "Marker": 3
    }, 
    "USC00025635": {
        "Lat": 34.6106, 
        "Lon": -111.8381, 
        "Marker": 3
    }, 
    "USC00025700": {
        "Lat": 33.5544, 
        "Lon": -111.4425, 
        "Marker": 5
    }, 
    "USC00025924": {
        "Lat": 31.4553, 
        "Lon": -110.9681, 
        "Marker": 2
    }, 
    "USC00026353": {
        "Lat": 31.9356, 
        "Lon": -109.8378, 
        "Marker": 1
    }, 
    "USC00026468": {
        "Lat": 34.7994, 
        "Lon": -109.885, 
        "Marker": 3
    }, 
    "USC00027281": {
        "Lat": 33.6731, 
        "Lon": -111.1508, 
        "Marker": 5
    }, 
    "USC00027390": {
        "Lat": 32.815, 
        "Lon": -109.6808, 
        "Marker": 6
    }, 
    "USC00027480": {
        "Lat": 33.1819, 
        "Lon": -110.5261, 
        "Marker": 1
    }, 
    "USC00027488": {
        "Lat": 35.2239, 
        "Lon": -109.3222, 
        "Marker": 5
    }, 
    "USC00027619": {
        "Lat": 31.4831, 
        "Lon": -111.5436, 
        "Marker": 2
    }, 
    "USC00028012": {
        "Lat": 34.5081, 
        "Lon": -110.0839, 
        "Marker": 5
    }, 
    "USC00028162": {
        "Lat": 34.1311, 
        "Lon": -109.275, 
        "Marker": 1
    }, 
    "USC00028499": {
        "Lat": 33.4258, 
        "Lon": -111.9217, 
        "Marker": 4
    }, 
    "USC00028619": {
        "Lat": 31.7119, 
        "Lon": -110.0686, 
        "Marker": 2
    }, 
    "USC00028865": {
        "Lat": 31.5678, 
        "Lon": -111.0497, 
        "Marker": 4
    }, 
    "USC00029158": {
        "Lat": 34.9281, 
        "Lon": -112.8097, 
        "Marker": 3
    }, 
    "USC00029287": {
        "Lat": 33.9792, 
        "Lon": -112.7403, 
        "Marker": 2
    }, 
    "USC00029542": {
        "Lat": 35.5247, 
        "Lon": -111.3703, 
        "Marker": 6
    }, 
    "USC00030130": {
        "Lat": 34.7961, 
        "Lon": -92.8417, 
        "Marker": 1
    }, 
    "USC00030764": {
        "Lat": 34.5697, 
        "Lon": -93.1947, 
        "Marker": 1
    }, 
    "USC00030936": {
        "Lat": 34.8822, 
        "Lon": -91.2153, 
        "Marker": 1
    }, 
    "USC00031132": {
        "Lat": 36.1092, 
        "Lon": -92.1636, 
        "Marker": 2
    }, 
    "USC00031152": {
        "Lat": 33.59, 
        "Lon": -92.8236, 
        "Marker": 2
    }, 
    "USC00031730": {
        "Lat": 33.1111, 
        "Lon": -91.9481, 
        "Marker": 2
    }, 
    "USC00031838": {
        "Lat": 35.2342, 
        "Lon": -93.1675, 
        "Marker": 1
    }, 
    "USC00032444": {
        "Lat": 36.1006, 
        "Lon": -94.1744, 
        "Marker": 1
    }, 
    "USC00032540": {
        "Lat": 33.8228, 
        "Lon": -92.3989, 
        "Marker": 1
    }, 
    "USC00033466": {
        "Lat": 34.5128, 
        "Lon": -93.0486, 
        "Marker": 1
    }, 
    "USC00033734": {
        "Lat": 35.8489, 
        "Lon": -90.6589, 
        "Marker": 1
    }, 
    "USC00034106": {
        "Lat": 36.4194, 
        "Lon": -92.9158, 
        "Marker": 1
    }, 
    "USC00034638": {
        "Lat": 34.7392, 
        "Lon": -90.7664, 
        "Marker": 1
    }, 
    "USC00034756": {
        "Lat": 34.5731, 
        "Lon": -94.2494, 
        "Marker": 1
    }, 
    "USC00035036": {
        "Lat": 36.3458, 
        "Lon": -92.3939, 
        "Marker": 1
    }, 
    "USC00035908": {
        "Lat": 33.8203, 
        "Lon": -93.3878, 
        "Marker": 3
    }, 
    "USC00036506": {
        "Lat": 35.2683, 
        "Lon": -91.7164, 
        "Marker": 1
    }, 
    "USC00036928": {
        "Lat": 35.3028, 
        "Lon": -93.6369, 
        "Marker": 2
    }, 
    "USC00040161": {
        "Lat": 41.4931, 
        "Lon": -120.5528, 
        "Marker": 1
    }, 
    "USC00040379": {
        "Lat": 37.0919, 
        "Lon": -119.5128, 
        "Marker": 1
    }, 
    "USC00040924": {
        "Lat": 33.6131, 
        "Lon": -114.5972, 
        "Marker": 4
    }, 
    "USC00040931": {
        "Lat": 39.3886, 
        "Lon": -120.0936, 
        "Marker": 2
    }, 
    "USC00041214": {
        "Lat": 40.8803, 
        "Lon": -121.6547, 
        "Marker": 1
    }, 
    "USC00041715": {
        "Lat": 39.6911, 
        "Lon": -121.8211, 
        "Marker": 2
    }, 
    "USC00041806": {
        "Lat": 38.9239, 
        "Lon": -122.5672, 
        "Marker": 1
    }, 
    "USC00041948": {
        "Lat": 39.1875, 
        "Lon": -122.0269, 
        "Marker": 1
    }, 
    "USC00042081": {
        "Lat": 39.8158, 
        "Lon": -123.2444, 
        "Marker": 1
    }, 
    "USC00042147": {
        "Lat": 41.7958, 
        "Lon": -124.2147, 
        "Marker": 2
    }, 
    "USC00042506": {
        "Lat": 39.9717, 
        "Lon": -120.0828, 
        "Marker": 1
    }, 
    "USC00042598": {
        "Lat": 33.8089, 
        "Lon": -115.4508, 
        "Marker": 1
    }, 
    "USC00042713": {
        "Lat": 32.7669, 
        "Lon": -115.5617, 
        "Marker": 4
    }, 
    "USC00043157": {
        "Lat": 41.8714, 
        "Lon": -120.1575, 
        "Marker": 1
    }, 
    "USC00043824": {
        "Lat": 40.9317, 
        "Lon": -121.5433, 
        "Marker": 1
    }, 
    "USC00043855": {
        "Lat": 33.7044, 
        "Lon": -115.6289, 
        "Marker": 1
    }, 
    "USC00044259": {
        "Lat": 33.7086, 
        "Lon": -116.2153, 
        "Marker": 2
    }, 
    "USC00044297": {
        "Lat": 34.1472, 
        "Lon": -115.1219, 
        "Marker": 2
    }, 
    "USC00044374": {
        "Lat": 41.2683, 
        "Lon": -120.2947, 
        "Marker": 1
    }, 
    "USC00044838": {
        "Lat": 41.7019, 
        "Lon": -121.5011, 
        "Marker": 1
    }, 
    "USC00044997": {
        "Lat": 37.6922, 
        "Lon": -121.7692, 
        "Marker": 1
    }, 
    "USC00045311": {
        "Lat": 40.5411, 
        "Lon": -121.5767, 
        "Marker": 2
    }, 
    "USC00045449": {
        "Lat": 41.2514, 
        "Lon": -122.1383, 
        "Marker": 1
    }, 
    "USC00045502": {
        "Lat": 33.5714, 
        "Lon": -116.0767, 
        "Marker": 1
    }, 
    "USC00046074": {
        "Lat": 38.2778, 
        "Lon": -122.2647, 
        "Marker": 1
    }, 
    "USC00046508": {
        "Lat": 41.3089, 
        "Lon": -123.5317, 
        "Marker": 1
    }, 
    "USC00046624": {
        "Lat": 34.5883, 
        "Lon": -118.0939, 
        "Marker": 1
    }, 
    "USC00046635": {
        "Lat": 33.8275, 
        "Lon": -116.5097, 
        "Marker": 1
    }, 
    "USC00046657": {
        "Lat": 33.3781, 
        "Lon": -116.84, 
        "Marker": 1
    }, 
    "USC00046699": {
        "Lat": 34.2903, 
        "Lon": -114.1708, 
        "Marker": 1
    }, 
    "USC00046730": {
        "Lat": 35.6278, 
        "Lon": -120.6856, 
        "Marker": 1
    }, 
    "USC00046943": {
        "Lat": 35.1597, 
        "Lon": -120.6831, 
        "Marker": 1
    }, 
    "USC00047109": {
        "Lat": 39.3619, 
        "Lon": -123.1286, 
        "Marker": 3
    }, 
    "USC00047253": {
        "Lat": 35.3692, 
        "Lon": -117.6525, 
        "Marker": 2
    }, 
    "USC00047888": {
        "Lat": 33.7442, 
        "Lon": -117.8667, 
        "Marker": 1
    }, 
    "USC00048135": {
        "Lat": 40.7142, 
        "Lon": -122.4161, 
        "Marker": 1
    }, 
    "USC00048587": {
        "Lat": 39.5861, 
        "Lon": -122.5342, 
        "Marker": 1
    }, 
    "USC00048758": {
        "Lat": 39.1678, 
        "Lon": -120.1428, 
        "Marker": 2
    }, 
    "USC00048999": {
        "Lat": 37.6819, 
        "Lon": -121.3467, 
        "Marker": 1
    }, 
    "USC00049035": {
        "Lat": 35.7636, 
        "Lon": -117.3908, 
        "Marker": 1
    }, 
    "USC00049152": {
        "Lat": 34.0697, 
        "Lon": -118.4428, 
        "Marker": 1
    }, 
    "USC00049490": {
        "Lat": 40.7222, 
        "Lon": -122.9331, 
        "Marker": 1
    }, 
    "USC00049699": {
        "Lat": 39.5231, 
        "Lon": -122.3058, 
        "Marker": 2
    }, 
    "USC00049866": {
        "Lat": 41.7036, 
        "Lon": -122.6408, 
        "Marker": 2
    }, 
    "USC00050214": {
        "Lat": 39.5008, 
        "Lon": -108.3794, 
        "Marker": 2
    }, 
    "USC00050454": {
        "Lat": 39.4047, 
        "Lon": -105.4767, 
        "Marker": 1
    }, 
    "USC00051071": {
        "Lat": 38.8247, 
        "Lon": -106.1275, 
        "Marker": 1
    }, 
    "USC00051179": {
        "Lat": 39.7403, 
        "Lon": -104.1275, 
        "Marker": 1
    }, 
    "USC00051294": {
        "Lat": 38.46, 
        "Lon": -105.2256, 
        "Marker": 3
    }, 
    "USC00051528": {
        "Lat": 39.2203, 
        "Lon": -105.2783, 
        "Marker": 2
    }, 
    "USC00051564": {
        "Lat": 38.8219, 
        "Lon": -102.3508, 
        "Marker": 2
    }, 
    "USC00051772": {
        "Lat": 39.1014, 
        "Lon": -108.7339, 
        "Marker": 5
    }, 
    "USC00051886": {
        "Lat": 37.3444, 
        "Lon": -108.5931, 
        "Marker": 2
    }, 
    "USC00051959": {
        "Lat": 38.8739, 
        "Lon": -106.9769, 
        "Marker": 2
    }, 
    "USC00052184": {
        "Lat": 37.6908, 
        "Lon": -106.3083, 
        "Marker": 1
    }, 
    "USC00052446": {
        "Lat": 38.4758, 
        "Lon": -102.7769, 
        "Marker": 1
    }, 
    "USC00053005": {
        "Lat": 40.6147, 
        "Lon": -105.1314, 
        "Marker": 1
    }, 
    "USC00053016": {
        "Lat": 37.2308, 
        "Lon": -108.0514, 
        "Marker": 3
    }, 
    "USC00053038": {
        "Lat": 40.26, 
        "Lon": -103.8156, 
        "Marker": 1
    }, 
    "USC00053359": {
        "Lat": 39.5181, 
        "Lon": -107.3172, 
        "Marker": 1
    }, 
    "USC00053541": {
        "Lat": 37.7333, 
        "Lon": -105.5119, 
        "Marker": 3
    }, 
    "USC00053662": {
        "Lat": 38.5253, 
        "Lon": -106.9672, 
        "Marker": 2
    }, 
    "USC00053951": {
        "Lat": 37.7717, 
        "Lon": -107.1097, 
        "Marker": 1
    }, 
    "USC00054076": {
        "Lat": 38.0517, 
        "Lon": -102.1317, 
        "Marker": 2
    }, 
    "USC00054603": {
        "Lat": 38.7658, 
        "Lon": -102.8031, 
        "Marker": 1
    }, 
    "USC00054770": {
        "Lat": 38.0936, 
        "Lon": -102.6306, 
        "Marker": 2
    }, 
    "USC00054834": {
        "Lat": 38.0636, 
        "Lon": -103.2153, 
        "Marker": 2
    }, 
    "USC00055446": {
        "Lat": 40.5158, 
        "Lon": -108.0947, 
        "Marker": 4
    }, 
    "USC00055706": {
        "Lat": 37.5811, 
        "Lon": -106.1872, 
        "Marker": 3
    }, 
    "USC00056266": {
        "Lat": 39.1136, 
        "Lon": -108.3506, 
        "Marker": 3
    }, 
    "USC00056832": {
        "Lat": 40.0894, 
        "Lon": -108.7717, 
        "Marker": 1
    }, 
    "USC00057167": {
        "Lat": 38.0392, 
        "Lon": -103.6933, 
        "Marker": 1
    }, 
    "USC00057287": {
        "Lat": 38.8611, 
        "Lon": -104.0939, 
        "Marker": 5
    }, 
    "USC00057309": {
        "Lat": 38.8417, 
        "Lon": -104.9742, 
        "Marker": 1
    }, 
    "USC00058157": {
        "Lat": 38.3422, 
        "Lon": -104.0567, 
        "Marker": 3
    }, 
    "USC00058429": {
        "Lat": 37.1786, 
        "Lon": -104.4869, 
        "Marker": 2
    }, 
    "USC00058582": {
        "Lat": 37.3842, 
        "Lon": -107.5822, 
        "Marker": 3
    }, 
    "USC00058781": {
        "Lat": 37.6303, 
        "Lon": -104.7956, 
        "Marker": 3
    }, 
    "USC00058839": {
        "Lat": 40.4256, 
        "Lon": -105.2103, 
        "Marker": 1
    }, 
    "USC00058931": {
        "Lat": 38.1311, 
        "Lon": -105.4661, 
        "Marker": 4
    }, 
    "USC00059243": {
        "Lat": 40.0714, 
        "Lon": -102.2325, 
        "Marker": 1
    }, 
    "USC00059295": {
        "Lat": 40.1236, 
        "Lon": -102.7217, 
        "Marker": 2
    }, 
    "USC00065910": {
        "Lat": 41.5269, 
        "Lon": -72.0642, 
        "Marker": 1
    }, 
    "USC00080369": {
        "Lat": 27.5947, 
        "Lon": -81.5267, 
        "Marker": 4
    }, 
    "USC00084366": {
        "Lat": 30.2875, 
        "Lon": -81.3928, 
        "Marker": 2
    }, 
    "USC00086414": {
        "Lat": 29.1639, 
        "Lon": -82.0778, 
        "Marker": 1
    }, 
    "USC00086880": {
        "Lat": 27.6089, 
        "Lon": -82.3478, 
        "Marker": 1
    }, 
    "USC00090979": {
        "Lat": 31.2239, 
        "Lon": -84.5553, 
        "Marker": 1
    }, 
    "USC00095863": {
        "Lat": 32.8753, 
        "Lon": -82.2156, 
        "Marker": 5
    }, 
    "USC00100282": {
        "Lat": 43.3572, 
        "Lon": -115.4522, 
        "Marker": 1
    }, 
    "USC00101079": {
        "Lat": 48.6928, 
        "Lon": -116.3103, 
        "Marker": 1
    }, 
    "USC00101363": {
        "Lat": 48.0864, 
        "Lon": -116.0572, 
        "Marker": 2
    }, 
    "USC00101514": {
        "Lat": 44.5228, 
        "Lon": -116.0481, 
        "Marker": 1
    }, 
    "USC00101956": {
        "Lat": 47.6822, 
        "Lon": -116.7967, 
        "Marker": 1
    }, 
    "USC00102260": {
        "Lat": 43.465, 
        "Lon": -113.5581, 
        "Marker": 1
    }, 
    "USC00102676": {
        "Lat": 43.7306, 
        "Lon": -111.1125, 
        "Marker": 2
    }, 
    "USC00102942": {
        "Lat": 43.8544, 
        "Lon": -116.4664, 
        "Marker": 1
    }, 
    "USC00103297": {
        "Lat": 43.0428, 
        "Lon": -112.4133, 
        "Marker": 1
    }, 
    "USC00103448": {
        "Lat": 44.1011, 
        "Lon": -115.9694, 
        "Marker": 2
    }, 
    "USC00103771": {
        "Lat": 45.9414, 
        "Lon": -116.1175, 
        "Marker": 1
    }, 
    "USC00104670": {
        "Lat": 42.7325, 
        "Lon": -114.5192, 
        "Marker": 2
    }, 
    "USC00105275": {
        "Lat": 42.1231, 
        "Lon": -111.3133, 
        "Marker": 2
    }, 
    "USC00105462": {
        "Lat": 43.9181, 
        "Lon": -113.6317, 
        "Marker": 1
    }, 
    "USC00105685": {
        "Lat": 44.5664, 
        "Lon": -113.8953, 
        "Marker": 1
    }, 
    "USC00105980": {
        "Lat": 42.6767, 
        "Lon": -113.5003, 
        "Marker": 1
    }, 
    "USC00106152": {
        "Lat": 46.7281, 
        "Lon": -116.9558, 
        "Marker": 2
    }, 
    "USC00106424": {
        "Lat": 46.2325, 
        "Lon": -116.243, 
        "Marker": 2
    }, 
    "USC00106877": {
        "Lat": 42.6283, 
        "Lon": -113.7622, 
        "Marker": 2
    }, 
    "USC00106891": {
        "Lat": 44.0764, 
        "Lon": -116.9311, 
        "Marker": 1
    }, 
    "USC00107040": {
        "Lat": 43.3086, 
        "Lon": -114.0667, 
        "Marker": 3
    }, 
    "USC00107264": {
        "Lat": 48.9994, 
        "Lon": -116.4992, 
        "Marker": 1
    }, 
    "USC00107386": {
        "Lat": 48.3511, 
        "Lon": -116.8353, 
        "Marker": 1
    }, 
    "USC00108062": {
        "Lat": 47.3164, 
        "Lon": -116.5789, 
        "Marker": 2
    }, 
    "USC00108380": {
        "Lat": 42.9383, 
        "Lon": -114.4169, 
        "Marker": 2
    }, 
    "USC00108818": {
        "Lat": 43.8867, 
        "Lon": -111.7367, 
        "Marker": 1
    }, 
    "USC00109065": {
        "Lat": 43.8564, 
        "Lon": -111.2769, 
        "Marker": 2
    }, 
    "USC00113879": {
        "Lat": 37.7408, 
        "Lon": -88.5244, 
        "Marker": 1
    }, 
    "USC00114442": {
        "Lat": 39.7353, 
        "Lon": -90.2153, 
        "Marker": 1
    }, 
    "USC00115833": {
        "Lat": 41.8039, 
        "Lon": -89.9744, 
        "Marker": 1
    }, 
    "USC00130112": {
        "Lat": 41.0656, 
        "Lon": -92.7867, 
        "Marker": 1
    }, 
    "USC00134389": {
        "Lat": 40.7275, 
        "Lon": -91.9683, 
        "Marker": 1
    }, 
    "USC00135131": {
        "Lat": 42.0494, 
        "Lon": -90.7489, 
        "Marker": 2
    }, 
    "USC00136327": {
        "Lat": 41.3214, 
        "Lon": -92.6467, 
        "Marker": 1
    }, 
    "USC00137161": {
        "Lat": 42.3969, 
        "Lon": -94.6292, 
        "Marker": 1
    }, 
    "USC00140865": {
        "Lat": 38.5636, 
        "Lon": -99.235, 
        "Marker": 1
    }, 
    "USC00141522": {
        "Lat": 37.8131, 
        "Lon": -100.3456, 
        "Marker": 3
    }, 
    "USC00141858": {
        "Lat": 38.3703, 
        "Lon": -96.5483, 
        "Marker": 1
    }, 
    "USC00142432": {
        "Lat": 37.0058, 
        "Lon": -101.8867, 
        "Marker": 1
    }, 
    "USC00142980": {
        "Lat": 37.9931, 
        "Lon": -100.8122, 
        "Marker": 3
    }, 
    "USC00143810": {
        "Lat": 39.6678, 
        "Lon": -95.52, 
        "Marker": 1
    }, 
    "USC00143837": {
        "Lat": 39.3533, 
        "Lon": -100.4397, 
        "Marker": 1
    }, 
    "USC00143855": {
        "Lat": 37.1639, 
        "Lon": -101.34, 
        "Marker": 1
    }, 
    "USC00143930": {
        "Lat": 37.9311, 
        "Lon": -98.0297, 
        "Marker": 1
    }, 
    "USC00144665": {
        "Lat": 38.4794, 
        "Lon": -101.3658, 
        "Marker": 1
    }, 
    "USC00144695": {
        "Lat": 37.0222, 
        "Lon": -100.9294, 
        "Marker": 4
    }, 
    "USC00145171": {
        "Lat": 37.285, 
        "Lon": -100.345, 
        "Marker": 2
    }, 
    "USC00145536": {
        "Lat": 37.1872, 
        "Lon": -95.4508, 
        "Marker": 2
    }, 
    "USC00145692": {
        "Lat": 38.4478, 
        "Lon": -99.91, 
        "Marker": 3
    }, 
    "USC00145888": {
        "Lat": 39.1131, 
        "Lon": -100.9447, 
        "Marker": 3
    }, 
    "USC00146076": {
        "Lat": 38.6361, 
        "Lon": -95.8031, 
        "Marker": 1
    }, 
    "USC00146435": {
        "Lat": 39.245, 
        "Lon": -99.3808, 
        "Marker": 2
    }, 
    "USC00146637": {
        "Lat": 39.0669, 
        "Lon": -100.2389, 
        "Marker": 1
    }, 
    "USC00147093": {
        "Lat": 39.7675, 
        "Lon": -101.8067, 
        "Marker": 1
    }, 
    "USC00147271": {
        "Lat": 38.4747, 
        "Lon": -100.9175, 
        "Marker": 1
    }, 
    "USC00147397": {
        "Lat": 38.8961, 
        "Lon": -101.7514, 
        "Marker": 1
    }, 
    "USC00147922": {
        "Lat": 37.4414, 
        "Lon": -100.9792, 
        "Marker": 5
    }, 
    "USC00148038": {
        "Lat": 37.9928, 
        "Lon": -101.7417, 
        "Marker": 1
    }, 
    "USC00148235": {
        "Lat": 38.4661, 
        "Lon": -101.7758, 
        "Marker": 3
    }, 
    "USC00148287": {
        "Lat": 37.5983, 
        "Lon": -101.2908, 
        "Marker": 2
    }, 
    "USC00148648": {
        "Lat": 39.4031, 
        "Lon": -99.4192, 
        "Marker": 1
    }, 
    "USC00161411": {
        "Lat": 32.5133, 
        "Lon": -92.3486, 
        "Marker": 2
    }, 
    "USC00165090": {
        "Lat": 32.8067, 
        "Lon": -91.173, 
        "Marker": 1
    }, 
    "USC00166394": {
        "Lat": 29.6833, 
        "Lon": -91.1761, 
        "Marker": 2
    }, 
    "USC00168539": {
        "Lat": 30.265, 
        "Lon": -89.7697, 
        "Marker": 2
    }, 
    "USC00170480": {
        "Lat": 44.4394, 
        "Lon": -68.9892, 
        "Marker": 2
    }, 
    "USC00171628": {
        "Lat": 44.9197, 
        "Lon": -69.2417, 
        "Marker": 1
    }, 
    "USC00172426": {
        "Lat": 44.9067, 
        "Lon": -66.9919, 
        "Marker": 1
    }, 
    "USC00172878": {
        "Lat": 47.2386, 
        "Lon": -68.6136, 
        "Marker": 1
    }, 
    "USC00174183": {
        "Lat": 44.6453, 
        "Lon": -67.6494, 
        "Marker": 1
    }, 
    "USC00179151": {
        "Lat": 44.5272, 
        "Lon": -69.6544, 
        "Marker": 1
    }, 
    "USC00179891": {
        "Lat": 45.1569, 
        "Lon": -67.4044, 
        "Marker": 1
    }, 
    "USC00190860": {
        "Lat": 42.0478, 
        "Lon": -71.005, 
        "Marker": 1
    }, 
    "USC00192501": {
        "Lat": 41.3853, 
        "Lon": -70.5181, 
        "Marker": 1
    }, 
    "USC00203769": {
        "Lat": 43.5908, 
        "Lon": -86.1056, 
        "Marker": 1
    }, 
    "USC00208800": {
        "Lat": 44.2542, 
        "Lon": -84.2011, 
        "Marker": 1
    }, 
    "USC00216787": {
        "Lat": 47.8881, 
        "Lon": -96.2658, 
        "Marker": 1
    }, 
    "USC00220488": {
        "Lat": 34.3061, 
        "Lon": -89.9806, 
        "Marker": 1
    }, 
    "USC00221094": {
        "Lat": 31.5447, 
        "Lon": -90.4581, 
        "Marker": 1
    }, 
    "USC00221389": {
        "Lat": 32.6714, 
        "Lon": -90.0361, 
        "Marker": 1
    }, 
    "USC00221707": {
        "Lat": 34.1864, 
        "Lon": -90.5572, 
        "Marker": 1
    }, 
    "USC00221962": {
        "Lat": 34.8792, 
        "Lon": -88.6178, 
        "Marker": 1
    }, 
    "USC00222896": {
        "Lat": 33.5628, 
        "Lon": -89.2358, 
        "Marker": 2
    }, 
    "USC00223645": {
        "Lat": 33.7608, 
        "Lon": -89.8136, 
        "Marker": 3
    }, 
    "USC00223887": {
        "Lat": 31.2547, 
        "Lon": -89.3392, 
        "Marker": 1
    }, 
    "USC00223975": {
        "Lat": 34.8039, 
        "Lon": -90.0103, 
        "Marker": 1
    }, 
    "USC00224001": {
        "Lat": 34.6189, 
        "Lon": -89.1911, 
        "Marker": 4
    }, 
    "USC00224377": {
        "Lat": 34.6989, 
        "Lon": -89.8214, 
        "Marker": 2
    }, 
    "USC00227111": {
        "Lat": 34.1381, 
        "Lon": -88.9983, 
        "Marker": 1
    }, 
    "USC00228445": {
        "Lat": 33.4311, 
        "Lon": -90.9108, 
        "Marker": 1
    }, 
    "USC00228998": {
        "Lat": 34.7281, 
        "Lon": -90.3683, 
        "Marker": 3
    }, 
    "USC00230789": {
        "Lat": 37.6167, 
        "Lon": -93.3911, 
        "Marker": 1
    }, 
    "USC00231037": {
        "Lat": 39.4247, 
        "Lon": -93.1331, 
        "Marker": 1
    }, 
    "USC00231275": {
        "Lat": 40.1433, 
        "Lon": -91.5158, 
        "Marker": 1
    }, 
    "USC00231340": {
        "Lat": 39.3594, 
        "Lon": -93.4886, 
        "Marker": 1
    }, 
    "USC00232503": {
        "Lat": 38.3486, 
        "Lon": -92.5808, 
        "Marker": 1
    }, 
    "USC00234705": {
        "Lat": 37.4933, 
        "Lon": -94.3147, 
        "Marker": 1
    }, 
    "USC00234825": {
        "Lat": 37.685, 
        "Lon": -92.6936, 
        "Marker": 1
    }, 
    "USC00235253": {
        "Lat": 37.3036, 
        "Lon": -89.9664, 
        "Marker": 2
    }, 
    "USC00235834": {
        "Lat": 37.1542, 
        "Lon": -92.2617, 
        "Marker": 2
    }, 
    "USC00235976": {
        "Lat": 36.8639, 
        "Lon": -94.36, 
        "Marker": 1
    }, 
    "USC00236460": {
        "Lat": 36.6597, 
        "Lon": -93.1261, 
        "Marker": 2
    }, 
    "USC00238223": {
        "Lat": 38.9664, 
        "Lon": -93.4194, 
        "Marker": 1
    }, 
    "USC00238712": {
        "Lat": 38.7842, 
        "Lon": -93.8008, 
        "Marker": 1
    }, 
    "USC00238777": {
        "Lat": 37.7822, 
        "Lon": -92.2689, 
        "Marker": 1
    }, 
    "USC00240375": {
        "Lat": 46.6456, 
        "Lon": -112.2656, 
        "Marker": 1
    }, 
    "USC00240780": {
        "Lat": 45.8328, 
        "Lon": -109.9503, 
        "Marker": 1
    }, 
    "USC00241102": {
        "Lat": 45.3261, 
        "Lon": -108.9092, 
        "Marker": 1
    }, 
    "USC00241552": {
        "Lat": 47.2194, 
        "Lon": -111.71, 
        "Marker": 1
    }, 
    "USC00241722": {
        "Lat": 48.5883, 
        "Lon": -109.2256, 
        "Marker": 1
    }, 
    "USC00241737": {
        "Lat": 47.8206, 
        "Lon": -112.1919, 
        "Marker": 2
    }, 
    "USC00243110": {
        "Lat": 48.4983, 
        "Lon": -109.8014, 
        "Marker": 2
    }, 
    "USC00243113": {
        "Lat": 47.8306, 
        "Lon": -110.6608, 
        "Marker": 3
    }, 
    "USC00243530": {
        "Lat": 48.5653, 
        "Lon": -110.3022, 
        "Marker": 1
    }, 
    "USC00243984": {
        "Lat": 47.3889, 
        "Lon": -115.4225, 
        "Marker": 1
    }, 
    "USC00244038": {
        "Lat": 44.8667, 
        "Lon": -111.3392, 
        "Marker": 1
    }, 
    "USC00244084": {
        "Lat": 48.08, 
        "Lon": -116.0014, 
        "Marker": 1
    }, 
    "USC00244386": {
        "Lat": 46.7392, 
        "Lon": -107.2078, 
        "Marker": 1
    }, 
    "USC00244522": {
        "Lat": 47.3144, 
        "Lon": -106.9103, 
        "Marker": 1
    }, 
    "USC00244558": {
        "Lat": 48.3042, 
        "Lon": -114.2636, 
        "Marker": 1
    }, 
    "USC00244954": {
        "Lat": 46.3619, 
        "Lon": -110.6003, 
        "Marker": 1
    }, 
    "USC00245015": {
        "Lat": 48.4036, 
        "Lon": -115.5392, 
        "Marker": 1
    }, 
    "USC00245020": {
        "Lat": 47.9733, 
        "Lon": -115.2239, 
        "Marker": 1
    }, 
    "USC00245043": {
        "Lat": 47.4083, 
        "Lon": -113.7125, 
        "Marker": 1
    }, 
    "USC00245153": {
        "Lat": 47.9303, 
        "Lon": -110.5067, 
        "Marker": 3
    }, 
    "USC00246472": {
        "Lat": 46.3158, 
        "Lon": -113.3, 
        "Marker": 2
    }, 
    "USC00246862": {
        "Lat": 45.9636, 
        "Lon": -109.2531, 
        "Marker": 2
    }, 
    "USC00246918": {
        "Lat": 45.1897, 
        "Lon": -109.2861, 
        "Marker": 1
    }, 
    "USC00247448": {
        "Lat": 47.2142, 
        "Lon": -113.5203, 
        "Marker": 1
    }, 
    "USC00247540": {
        "Lat": 47.5319, 
        "Lon": -110.5769, 
        "Marker": 2
    }, 
    "USC00248021": {
        "Lat": 47.4775, 
        "Lon": -111.7406, 
        "Marker": 1
    }, 
    "USC00248233": {
        "Lat": 48.31, 
        "Lon": -111.0878, 
        "Marker": 5
    }, 
    "USC00249240": {
        "Lat": 45.3128, 
        "Lon": -107.9383, 
        "Marker": 3
    }, 
    "USC00250640": {
        "Lat": 40.1306, 
        "Lon": -99.8278, 
        "Marker": 1
    }, 
    "USC00254440": {
        "Lat": 41.2453, 
        "Lon": -103.6344, 
        "Marker": 1
    }, 
    "USC00254455": {
        "Lat": 41.2097, 
        "Lon": -101.6706, 
        "Marker": 3
    }, 
    "USC00255590": {
        "Lat": 41.9481, 
        "Lon": -103.7008, 
        "Marker": 1
    }, 
    "USC00256570": {
        "Lat": 40.1217, 
        "Lon": -96.1558, 
        "Marker": 2
    }, 
    "USC00257830": {
        "Lat": 41.2294, 
        "Lon": -103.0214, 
        "Marker": 1
    }, 
    "USC00260507": {
        "Lat": 39.4931, 
        "Lon": -117.0675, 
        "Marker": 1
    }, 
    "USC00260795": {
        "Lat": 40.5903, 
        "Lon": -116.475, 
        "Marker": 2
    }, 
    "USC00261485": {
        "Lat": 39.1253, 
        "Lon": -119.7678, 
        "Marker": 2
    }, 
    "USC00262229": {
        "Lat": 41.9892, 
        "Lon": -118.6339, 
        "Marker": 2
    }, 
    "USC00262780": {
        "Lat": 39.4572, 
        "Lon": -118.7811, 
        "Marker": 2
    }, 
    "USC00263205": {
        "Lat": 39.0753, 
        "Lon": -119.9411, 
        "Marker": 3
    }, 
    "USC00263957": {
        "Lat": 40.6564, 
        "Lon": -118.1631, 
        "Marker": 2
    }, 
    "USC00264349": {
        "Lat": 39.4689, 
        "Lon": -119.0644, 
        "Marker": 4
    }, 
    "USC00264527": {
        "Lat": 41.5167, 
        "Lon": -118.7192, 
        "Marker": 2
    }, 
    "USC00264698": {
        "Lat": 40.1906, 
        "Lon": -118.4767, 
        "Marker": 3
    }, 
    "USC00265168": {
        "Lat": 38.3844, 
        "Lon": -118.1056, 
        "Marker": 7
    }, 
    "USC00265352": {
        "Lat": 41.2783, 
        "Lon": -114.1708, 
        "Marker": 2
    }, 
    "USC00265818": {
        "Lat": 41.5683, 
        "Lon": -117.8389, 
        "Marker": 1
    }, 
    "USC00266252": {
        "Lat": 37.9344, 
        "Lon": -114.45, 
        "Marker": 3
    }, 
    "USC00267192": {
        "Lat": 40.4661, 
        "Lon": -118.3047, 
        "Marker": 1
    }, 
    "USC00267369": {
        "Lat": 35.4661, 
        "Lon": -114.9217, 
        "Marker": 1
    }, 
    "USC00268186": {
        "Lat": 38.6944, 
        "Lon": -119.5453, 
        "Marker": 3
    }, 
    "USC00268346": {
        "Lat": 41.3144, 
        "Lon": -116.2225, 
        "Marker": 1
    }, 
    "USC00268761": {
        "Lat": 39.3128, 
        "Lon": -119.6483, 
        "Marker": 1
    }, 
    "USC00269229": {
        "Lat": 38.9992, 
        "Lon": -119.1575, 
        "Marker": 1
    }, 
    "USC00274399": {
        "Lat": 42.9389, 
        "Lon": -72.3247, 
        "Marker": 1
    }, 
    "USC00290041": {
        "Lat": 36.2403, 
        "Lon": -106.4278, 
        "Marker": 1
    }, 
    "USC00290245": {
        "Lat": 36.0908, 
        "Lon": -106.0567, 
        "Marker": 6
    }, 
    "USC00290377": {
        "Lat": 35.8742, 
        "Lon": -103.1819, 
        "Marker": 1
    }, 
    "USC00290640": {
        "Lat": 34.075, 
        "Lon": -107.6211, 
        "Marker": 3
    }, 
    "USC00290692": {
        "Lat": 36.835, 
        "Lon": -108.0006, 
        "Marker": 4
    }, 
    "USC00290983": {
        "Lat": 33.9114, 
        "Lon": -106.3494, 
        "Marker": 2
    }, 
    "USC00291063": {
        "Lat": 36.6669, 
        "Lon": -107.9603, 
        "Marker": 4
    }, 
    "USC00291630": {
        "Lat": 36.7408, 
        "Lon": -105.5956, 
        "Marker": 4
    }, 
    "USC00291664": {
        "Lat": 36.9178, 
        "Lon": -106.5781, 
        "Marker": 3
    }, 
    "USC00291813": {
        "Lat": 36.4661, 
        "Lon": -104.9456, 
        "Marker": 4
    }, 
    "USC00291963": {
        "Lat": 34.5989, 
        "Lon": -103.2161, 
        "Marker": 1
    }, 
    "USC00292510": {
        "Lat": 35.1842, 
        "Lon": -105.0569, 
        "Marker": 2
    }, 
    "USC00292785": {
        "Lat": 35.0381, 
        "Lon": -108.3492, 
        "Marker": 3
    }, 
    "USC00292837": {
        "Lat": 36.5928, 
        "Lon": -106.73, 
        "Marker": 2
    }, 
    "USC00293488": {
        "Lat": 35.8917, 
        "Lon": -105.4481, 
        "Marker": 2
    }, 
    "USC00293649": {
        "Lat": 34.2594, 
        "Lon": -106.0931, 
        "Marker": 2
    }, 
    "USC00293706": {
        "Lat": 36.5939, 
        "Lon": -103.6192, 
        "Marker": 3
    }, 
    "USC00294346": {
        "Lat": 32.1103, 
        "Lon": -103.1872, 
        "Marker": 2
    }, 
    "USC00294742": {
        "Lat": 36.9825, 
        "Lon": -104.3753, 
        "Marker": 5
    }, 
    "USC00295084": {
        "Lat": 35.8644, 
        "Lon": -106.3214, 
        "Marker": 1
    }, 
    "USC00295150": {
        "Lat": 34.7675, 
        "Lon": -106.7611, 
        "Marker": 1
    }, 
    "USC00295490": {
        "Lat": 36.5697, 
        "Lon": -104.5867, 
        "Marker": 1
    }, 
    "USC00295560": {
        "Lat": 35.3364, 
        "Lon": -108.4447, 
        "Marker": 2
    }, 
    "USC00295617": {
        "Lat": 34.4278, 
        "Lon": -103.625, 
        "Marker": 1
    }, 
    "USC00295965": {
        "Lat": 34.5208, 
        "Lon": -106.2606, 
        "Marker": 1
    }, 
    "USC00296435": {
        "Lat": 32.3789, 
        "Lon": -106.0925, 
        "Marker": 2
    }, 
    "USC00296465": {
        "Lat": 36.3339, 
        "Lon": -107.8408, 
        "Marker": 2
    }, 
    "USC00296619": {
        "Lat": 36.2994, 
        "Lon": -103.7408, 
        "Marker": 3
    }, 
    "USC00296676": {
        "Lat": 35.5489, 
        "Lon": -105.6886, 
        "Marker": 3
    }, 
    "USC00296687": {
        "Lat": 34.6153, 
        "Lon": -105.4739, 
        "Marker": 2
    }, 
    "USC00297180": {
        "Lat": 34.3447, 
        "Lon": -108.4922, 
        "Marker": 4
    }, 
    "USC00297279": {
        "Lat": 36.9194, 
        "Lon": -104.4325, 
        "Marker": 1
    }, 
    "USC00297323": {
        "Lat": 36.71, 
        "Lon": -105.4164, 
        "Marker": 3
    }, 
    "USC00297340": {
        "Lat": 32.7047, 
        "Lon": -108.7281, 
        "Marker": 2
    }, 
    "USC00297386": {
        "Lat": 33.7158, 
        "Lon": -108.7769, 
        "Marker": 1
    }, 
    "USC00298501": {
        "Lat": 36.3628, 
        "Lon": -104.585, 
        "Marker": 1
    }, 
    "USC00298535": {
        "Lat": 32.2822, 
        "Lon": -106.7597, 
        "Marker": 2
    }, 
    "USC00298713": {
        "Lat": 33.2422, 
        "Lon": -103.3611, 
        "Marker": 2
    }, 
    "USC00299686": {
        "Lat": 32.7822, 
        "Lon": -106.1758, 
        "Marker": 2
    }, 
    "USC00299820": {
        "Lat": 35.9478, 
        "Lon": -106.7469, 
        "Marker": 5
    }, 
    "USC00301966": {
        "Lat": 44.7192, 
        "Lon": -73.7206, 
        "Marker": 1
    }, 
    "USC00303025": {
        "Lat": 42.3297, 
        "Lon": -78.4633, 
        "Marker": 1
    }, 
    "USC00303284": {
        "Lat": 43.3247, 
        "Lon": -73.6781, 
        "Marker": 1
    }, 
    "USC00303773": {
        "Lat": 42.7742, 
        "Lon": -77.6083, 
        "Marker": 1
    }, 
    "USC00307842": {
        "Lat": 43.2078, 
        "Lon": -77.0128, 
        "Marker": 2
    }, 
    "USC00310506": {
        "Lat": 36.1617, 
        "Lon": -81.8742, 
        "Marker": 1
    }, 
    "USC00312837": {
        "Lat": 35.5406, 
        "Lon": -82.6531, 
        "Marker": 1
    }, 
    "USC00314938": {
        "Lat": 35.915, 
        "Lon": -81.5378, 
        "Marker": 1
    }, 
    "USC00316349": {
        "Lat": 35.1075, 
        "Lon": -75.9872, 
        "Marker": 3
    }, 
    "USC00323217": {
        "Lat": 48.4583, 
        "Lon": -101.5697, 
        "Marker": 1
    }, 
    "USC00326315": {
        "Lat": 46.5414, 
        "Lon": -102.8692, 
        "Marker": 1
    }, 
    "USC00329246": {
        "Lat": 47.6, 
        "Lon": -103.2597, 
        "Marker": 1
    }, 
    "USC00336465": {
        "Lat": 41.1247, 
        "Lon": -84.5919, 
        "Marker": 1
    }, 
    "USC00336781": {
        "Lat": 38.7569, 
        "Lon": -82.8872, 
        "Marker": 1
    }, 
    "USC00340224": {
        "Lat": 35.0619, 
        "Lon": -98.1989, 
        "Marker": 5
    }, 
    "USC00340755": {
        "Lat": 36.5297, 
        "Lon": -97.4472, 
        "Marker": 3
    }, 
    "USC00340908": {
        "Lat": 36.7236, 
        "Lon": -102.4806, 
        "Marker": 3
    }, 
    "USC00342318": {
        "Lat": 35.9803, 
        "Lon": -96.7758, 
        "Marker": 2
    }, 
    "USC00342912": {
        "Lat": 36.4194, 
        "Lon": -97.8747, 
        "Marker": 2
    }, 
    "USC00343358": {
        "Lat": 36.7647, 
        "Lon": -99.1128, 
        "Marker": 4
    }, 
    "USC00343489": {
        "Lat": 36.85, 
        "Lon": -100.0569, 
        "Marker": 5
    }, 
    "USC00343628": {
        "Lat": 36.5914, 
        "Lon": -101.6181, 
        "Marker": 4
    }, 
    "USC00344001": {
        "Lat": 34.2333, 
        "Lon": -97.4203, 
        "Marker": 4
    }, 
    "USC00344019": {
        "Lat": 36.5381, 
        "Lon": -98.2661, 
        "Marker": 2
    }, 
    "USC00344298": {
        "Lat": 36.865, 
        "Lon": -101.2103, 
        "Marker": 3
    }, 
    "USC00344451": {
        "Lat": 33.9336, 
        "Lon": -94.8278, 
        "Marker": 1
    }, 
    "USC00345563": {
        "Lat": 33.8761, 
        "Lon": -97.1642, 
        "Marker": 1
    }, 
    "USC00346139": {
        "Lat": 36.2283, 
        "Lon": -99.17, 
        "Marker": 5
    }, 
    "USC00346935": {
        "Lat": 36.6692, 
        "Lon": -96.3472, 
        "Marker": 3
    }, 
    "USC00347862": {
        "Lat": 35.4572, 
        "Lon": -94.8047, 
        "Marker": 1
    }, 
    "USC00348708": {
        "Lat": 36.0381, 
        "Lon": -98.9592, 
        "Marker": 2
    }, 
    "USC00349364": {
        "Lat": 35.8578, 
        "Lon": -98.4139, 
        "Marker": 1
    }, 
    "USC00349724": {
        "Lat": 34.9417, 
        "Lon": -94.7039, 
        "Marker": 1
    }, 
    "USC00350694": {
        "Lat": 44.0569, 
        "Lon": -121.285, 
        "Marker": 4
    }, 
    "USC00350723": {
        "Lat": 43.9092, 
        "Lon": -118.1522, 
        "Marker": 5
    }, 
    "USC00351546": {
        "Lat": 43.2292, 
        "Lon": -121.7894, 
        "Marker": 2
    }, 
    "USC00351643": {
        "Lat": 46.1081, 
        "Lon": -123.2058, 
        "Marker": 1
    }, 
    "USC00351765": {
        "Lat": 45.2325, 
        "Lon": -120.1817, 
        "Marker": 3
    }, 
    "USC00351862": {
        "Lat": 44.6342, 
        "Lon": -123.19, 
        "Marker": 1
    }, 
    "USC00351897": {
        "Lat": 43.7917, 
        "Lon": -123.0275, 
        "Marker": 1
    }, 
    "USC00351902": {
        "Lat": 43.7178, 
        "Lon": -123.0578, 
        "Marker": 1
    }, 
    "USC00351926": {
        "Lat": 45.2964, 
        "Lon": -117.7903, 
        "Marker": 2
    }, 
    "USC00351946": {
        "Lat": 42.8967, 
        "Lon": -122.1328, 
        "Marker": 2
    }, 
    "USC00352112": {
        "Lat": 44.9464, 
        "Lon": -123.2911, 
        "Marker": 1
    }, 
    "USC00352292": {
        "Lat": 44.7242, 
        "Lon": -122.2547, 
        "Marker": 4
    }, 
    "USC00352374": {
        "Lat": 43.7822, 
        "Lon": -122.9631, 
        "Marker": 1
    }, 
    "USC00352693": {
        "Lat": 45.2689, 
        "Lon": -122.3186, 
        "Marker": 2
    }, 
    "USC00352867": {
        "Lat": 44.0494, 
        "Lon": -123.3703, 
        "Marker": 3
    }, 
    "USC00353038": {
        "Lat": 44.9983, 
        "Lon": -120.2175, 
        "Marker": 1
    }, 
    "USC00353402": {
        "Lat": 45.3014, 
        "Lon": -121.7417, 
        "Marker": 6
    }, 
    "USC00353542": {
        "Lat": 44.5175, 
        "Lon": -120.9389, 
        "Marker": 2
    }, 
    "USC00353604": {
        "Lat": 44.8772, 
        "Lon": -117.1094, 
        "Marker": 2
    }, 
    "USC00353692": {
        "Lat": 42.5483, 
        "Lon": -119.6556, 
        "Marker": 2
    }, 
    "USC00353770": {
        "Lat": 45.4486, 
        "Lon": -122.1547, 
        "Marker": 1
    }, 
    "USC00353827": {
        "Lat": 45.3653, 
        "Lon": -119.5639, 
        "Marker": 4
    }, 
    "USC00353847": {
        "Lat": 45.8289, 
        "Lon": -119.2636, 
        "Marker": 5
    }, 
    "USC00354003": {
        "Lat": 45.6847, 
        "Lon": -121.5175, 
        "Marker": 4
    }, 
    "USC00354098": {
        "Lat": 44.3564, 
        "Lon": -117.255, 
        "Marker": 5
    }, 
    "USC00354291": {
        "Lat": 44.4233, 
        "Lon": -118.9594, 
        "Marker": 1
    }, 
    "USC00354811": {
        "Lat": 44.1014, 
        "Lon": -122.6886, 
        "Marker": 2
    }, 
    "USC00355050": {
        "Lat": 43.9144, 
        "Lon": -122.76, 
        "Marker": 1
    }, 
    "USC00355139": {
        "Lat": 44.6167, 
        "Lon": -121.0011, 
        "Marker": 6
    }, 
    "USC00355160": {
        "Lat": 43.9794, 
        "Lon": -117.0247, 
        "Marker": 3
    }, 
    "USC00355162": {
        "Lat": 43.265, 
        "Lon": -118.8447, 
        "Marker": 3
    }, 
    "USC00355221": {
        "Lat": 44.6125, 
        "Lon": -121.9486, 
        "Marker": 5
    }, 
    "USC00355362": {
        "Lat": 44.1792, 
        "Lon": -122.1164, 
        "Marker": 2
    }, 
    "USC00355593": {
        "Lat": 45.9428, 
        "Lon": -118.4089, 
        "Marker": 5
    }, 
    "USC00355734": {
        "Lat": 45.4825, 
        "Lon": -120.7236, 
        "Marker": 3
    }, 
    "USC00356179": {
        "Lat": 43.8764, 
        "Lon": -116.9903, 
        "Marker": 1
    }, 
    "USC00356213": {
        "Lat": 43.7428, 
        "Lon": -122.4433, 
        "Marker": 3
    }, 
    "USC00356243": {
        "Lat": 44.3964, 
        "Lon": -120.4264, 
        "Marker": 4
    }, 
    "USC00356294": {
        "Lat": 44.0439, 
        "Lon": -116.9717, 
        "Marker": 4
    }, 
    "USC00356334": {
        "Lat": 45.3558, 
        "Lon": -122.6047, 
        "Marker": 2
    }, 
    "USC00356405": {
        "Lat": 43.65, 
        "Lon": -117.2467, 
        "Marker": 1
    }, 
    "USC00356532": {
        "Lat": 44.7275, 
        "Lon": -121.2506, 
        "Marker": 2
    }, 
    "USC00356540": {
        "Lat": 45.7206, 
        "Lon": -118.6264, 
        "Marker": 2
    }, 
    "USC00356634": {
        "Lat": 45.4756, 
        "Lon": -118.8253, 
        "Marker": 5
    }, 
    "USC00356883": {
        "Lat": 44.3022, 
        "Lon": -120.8081, 
        "Marker": 5
    }, 
    "USC00357310": {
        "Lat": 42.8592, 
        "Lon": -117.6569, 
        "Marker": 2
    }, 
    "USC00357809": {
        "Lat": 44.8728, 
        "Lon": -122.6486, 
        "Marker": 2
    }, 
    "USC00357857": {
        "Lat": 44.2842, 
        "Lon": -121.5486, 
        "Marker": 2
    }, 
    "USC00358095": {
        "Lat": 44.7892, 
        "Lon": -122.8142, 
        "Marker": 2
    }, 
    "USC00358173": {
        "Lat": 42.9592, 
        "Lon": -120.7897, 
        "Marker": 2
    }, 
    "USC00358466": {
        "Lat": 45.1219, 
        "Lon": -122.07, 
        "Marker": 5
    }, 
    "USC00358536": {
        "Lat": 43.275, 
        "Lon": -122.4497, 
        "Marker": 3
    }, 
    "USC00358634": {
        "Lat": 45.5533, 
        "Lon": -122.3886, 
        "Marker": 1
    }, 
    "USC00359316": {
        "Lat": 43.6825, 
        "Lon": -121.6875, 
        "Marker": 3
    }, 
    "USC00362183": {
        "Lat": 40.1275, 
        "Lon": -79.4058, 
        "Marker": 1
    }, 
    "USC00388405": {
        "Lat": 32.76, 
        "Lon": -79.8489, 
        "Marker": 2
    }, 
    "USC00403074": {
        "Lat": 35.15, 
        "Lon": -86.5411, 
        "Marker": 1
    }, 
    "USC00403280": {
        "Lat": 35.9417, 
        "Lon": -86.8686, 
        "Marker": 1
    }, 
    "USC00403679": {
        "Lat": 36.1056, 
        "Lon": -82.8436, 
        "Marker": 2
    }, 
    "USC00405089": {
        "Lat": 35.2436, 
        "Lon": -87.3508, 
        "Marker": 1
    }, 
    "USC00406292": {
        "Lat": 36.4739, 
        "Lon": -81.8033, 
        "Marker": 1
    }, 
    "USC00407359": {
        "Lat": 36.5875, 
        "Lon": -86.5258, 
        "Marker": 1
    }, 
    "USC00407459": {
        "Lat": 35.1842, 
        "Lon": -87.0422, 
        "Marker": 3
    }, 
    "USC00408179": {
        "Lat": 35.9297, 
        "Lon": -83.5983, 
        "Marker": 1
    }, 
    "USC00408246": {
        "Lat": 35.4922, 
        "Lon": -86.4775, 
        "Marker": 1
    }, 
    "USC00409155": {
        "Lat": 35.3453, 
        "Lon": -86.2089, 
        "Marker": 1
    }, 
    "USC00410498": {
        "Lat": 30.9844, 
        "Lon": -103.7403, 
        "Marker": 5
    }, 
    "USC00410569": {
        "Lat": 28.9797, 
        "Lon": -95.975, 
        "Marker": 1
    }, 
    "USC00410639": {
        "Lat": 28.4575, 
        "Lon": -97.7061, 
        "Marker": 1
    }, 
    "USC00410902": {
        "Lat": 29.7986, 
        "Lon": -98.7353, 
        "Marker": 1
    }, 
    "USC00410923": {
        "Lat": 33.6403, 
        "Lon": -96.1661, 
        "Marker": 5
    }, 
    "USC00410958": {
        "Lat": 35.6364, 
        "Lon": -101.4542, 
        "Marker": 2
    }, 
    "USC00410984": {
        "Lat": 33.5511, 
        "Lon": -97.8472, 
        "Marker": 4
    }, 
    "USC00411048": {
        "Lat": 30.1592, 
        "Lon": -96.3972, 
        "Marker": 1
    }, 
    "USC00411063": {
        "Lat": 33.2064, 
        "Lon": -97.7761, 
        "Marker": 2
    }, 
    "USC00411128": {
        "Lat": 33.1908, 
        "Lon": -102.2681, 
        "Marker": 2
    }, 
    "USC00411500": {
        "Lat": 32.1614, 
        "Lon": -94.3397, 
        "Marker": 2
    }, 
    "USC00411596": {
        "Lat": 31.2581, 
        "Lon": -95.9744, 
        "Marker": 1
    }, 
    "USC00411875": {
        "Lat": 31.8281, 
        "Lon": -99.4339, 
        "Marker": 1
    }, 
    "USC00412019": {
        "Lat": 32.1225, 
        "Lon": -96.4867, 
        "Marker": 1
    }, 
    "USC00412121": {
        "Lat": 33.6517, 
        "Lon": -101.245, 
        "Marker": 1
    }, 
    "USC00412173": {
        "Lat": 29.0892, 
        "Lon": -97.3433, 
        "Marker": 2
    }, 
    "USC00412225": {
        "Lat": 32.9203, 
        "Lon": -94.7225, 
        "Marker": 1
    }, 
    "USC00412266": {
        "Lat": 29.0567, 
        "Lon": -96.2319, 
        "Marker": 2
    }, 
    "USC00412394": {
        "Lat": 33.8167, 
        "Lon": -96.5667, 
        "Marker": 2
    }, 
    "USC00412404": {
        "Lat": 33.1992, 
        "Lon": -97.105, 
        "Marker": 1
    }, 
    "USC00412617": {
        "Lat": 35.8731, 
        "Lon": -101.9725, 
        "Marker": 1
    }, 
    "USC00413183": {
        "Lat": 29.6339, 
        "Lon": -97.0644, 
        "Marker": 4
    }, 
    "USC00413214": {
        "Lat": 33.985, 
        "Lon": -101.3339, 
        "Marker": 1
    }, 
    "USC00413225": {
        "Lat": 36.4328, 
        "Lon": -100.1369, 
        "Marker": 2
    }, 
    "USC00413340": {
        "Lat": 28.9844, 
        "Lon": -95.3808, 
        "Marker": 3
    }, 
    "USC00413618": {
        "Lat": 28.6617, 
        "Lon": -97.385, 
        "Marker": 3
    }, 
    "USC00413668": {
        "Lat": 33.1203, 
        "Lon": -98.5669, 
        "Marker": 1
    }, 
    "USC00413734": {
        "Lat": 33.1678, 
        "Lon": -96.0983, 
        "Marker": 1
    }, 
    "USC00414254": {
        "Lat": 29.3364, 
        "Lon": -99.1383, 
        "Marker": 1
    }, 
    "USC00414517": {
        "Lat": 33.2206, 
        "Lon": -98.1561, 
        "Marker": 2
    }, 
    "USC00415013": {
        "Lat": 32.7228, 
        "Lon": -101.9456, 
        "Marker": 2
    }, 
    "USC00415094": {
        "Lat": 33.0353, 
        "Lon": -96.4861, 
        "Marker": 2
    }, 
    "USC00415183": {
        "Lat": 33.55, 
        "Lon": -102.3758, 
        "Marker": 1
    }, 
    "USC00415271": {
        "Lat": 30.7394, 
        "Lon": -94.9256, 
        "Marker": 2
    }, 
    "USC00415272": {
        "Lat": 30.7425, 
        "Lon": -98.6542, 
        "Marker": 1
    }, 
    "USC00415429": {
        "Lat": 29.6756, 
        "Lon": -97.6578, 
        "Marker": 3
    }, 
    "USC00415611": {
        "Lat": 31.3336, 
        "Lon": -96.8581, 
        "Marker": 1
    }, 
    "USC00415658": {
        "Lat": 34.0044, 
        "Lon": -100.825, 
        "Marker": 2
    }, 
    "USC00415707": {
        "Lat": 31.1331, 
        "Lon": -102.2217, 
        "Marker": 2
    }, 
    "USC00415822": {
        "Lat": 30.9144, 
        "Lon": -99.7958, 
        "Marker": 1
    }, 
    "USC00415891": {
        "Lat": 32.0186, 
        "Lon": -102.0258, 
        "Marker": 2
    }, 
    "USC00416135": {
        "Lat": 34.2192, 
        "Lon": -102.7328, 
        "Marker": 1
    }, 
    "USC00416276": {
        "Lat": 29.7192, 
        "Lon": -98.1189, 
        "Marker": 6
    }, 
    "USC00416368": {
        "Lat": 29.2283, 
        "Lon": -97.7675, 
        "Marker": 2
    }, 
    "USC00416644": {
        "Lat": 34.1797, 
        "Lon": -102.1356, 
        "Marker": 3
    }, 
    "USC00416794": {
        "Lat": 33.6744, 
        "Lon": -95.5586, 
        "Marker": 1
    }, 
    "USC00417074": {
        "Lat": 33.1869, 
        "Lon": -102.8281, 
        "Marker": 2
    }, 
    "USC00417079": {
        "Lat": 34.1892, 
        "Lon": -101.7022, 
        "Marker": 2
    }, 
    "USC00418201": {
        "Lat": 32.7131, 
        "Lon": -102.6597, 
        "Marker": 1
    }, 
    "USC00418354": {
        "Lat": 28.0353, 
        "Lon": -97.4972, 
        "Marker": 1
    }, 
    "USC00418415": {
        "Lat": 30.0067, 
        "Lon": -97.1689, 
        "Marker": 4
    }, 
    "USC00418433": {
        "Lat": 32.71, 
        "Lon": -100.9111, 
        "Marker": 2
    }, 
    "USC00418692": {
        "Lat": 36.3372, 
        "Lon": -102.0753, 
        "Marker": 1
    }, 
    "USC00418743": {
        "Lat": 33.1481, 
        "Lon": -95.6269, 
        "Marker": 8
    }, 
    "USC00418818": {
        "Lat": 33.1714, 
        "Lon": -101.7981, 
        "Marker": 1
    }, 
    "USC00419175": {
        "Lat": 34.5269, 
        "Lon": -101.8392, 
        "Marker": 2
    }, 
    "USC00419295": {
        "Lat": 31.0417, 
        "Lon": -104.8372, 
        "Marker": 1
    }, 
    "USC00419491": {
        "Lat": 30.3236, 
        "Lon": -96.1594, 
        "Marker": 1
    }, 
    "USC00419532": {
        "Lat": 32.7483, 
        "Lon": -97.77, 
        "Marker": 1
    }, 
    "USC00419715": {
        "Lat": 31.8611, 
        "Lon": -97.375, 
        "Marker": 1
    }, 
    "USC00419800": {
        "Lat": 32.7019, 
        "Lon": -96.015, 
        "Marker": 5
    }, 
    "USC00420074": {
        "Lat": 40.3561, 
        "Lon": -110.2878, 
        "Marker": 1
    }, 
    "USC00420086": {
        "Lat": 37.4403, 
        "Lon": -112.4819, 
        "Marker": 1
    }, 
    "USC00420730": {
        "Lat": 38.7075, 
        "Lon": -112.9539, 
        "Marker": 1
    }, 
    "USC00420738": {
        "Lat": 37.6131, 
        "Lon": -109.4847, 
        "Marker": 2
    }, 
    "USC00420788": {
        "Lat": 37.2825, 
        "Lon": -109.5575, 
        "Marker": 1
    }, 
    "USC00420849": {
        "Lat": 37.905, 
        "Lon": -111.42, 
        "Marker": 2
    }, 
    "USC00421008": {
        "Lat": 37.6411, 
        "Lon": -112.1689, 
        "Marker": 2
    }, 
    "USC00421214": {
        "Lat": 39.2078, 
        "Lon": -111.0125, 
        "Marker": 3
    }, 
    "USC00421308": {
        "Lat": 37.7158, 
        "Lon": -109.0828, 
        "Marker": 2
    }, 
    "USC00422057": {
        "Lat": 40.4044, 
        "Lon": -111.5289, 
        "Marker": 1
    }, 
    "USC00422173": {
        "Lat": 40.4378, 
        "Lon": -109.3045, 
        "Marker": 2
    }, 
    "USC00422253": {
        "Lat": 40.1678, 
        "Lon": -110.395, 
        "Marker": 2
    }, 
    "USC00422385": {
        "Lat": 40.9656, 
        "Lon": -111.435, 
        "Marker": 2
    }, 
    "USC00422592": {
        "Lat": 37.7686, 
        "Lon": -111.5978, 
        "Marker": 1
    }, 
    "USC00422798": {
        "Lat": 39.0875, 
        "Lon": -111.1325, 
        "Marker": 2
    }, 
    "USC00422828": {
        "Lat": 38.9664, 
        "Lon": -112.3278, 
        "Marker": 3
    }, 
    "USC00424100": {
        "Lat": 37.3858, 
        "Lon": -109.075, 
        "Marker": 3
    }, 
    "USC00424174": {
        "Lat": 40.0378, 
        "Lon": -113.9886, 
        "Marker": 2
    }, 
    "USC00424508": {
        "Lat": 37.0286, 
        "Lon": -112.5367, 
        "Marker": 1
    }, 
    "USC00425402": {
        "Lat": 39.2583, 
        "Lon": -111.6306, 
        "Marker": 1
    }, 
    "USC00425582": {
        "Lat": 37.1497, 
        "Lon": -109.8675, 
        "Marker": 3
    }, 
    "USC00425733": {
        "Lat": 38.5744, 
        "Lon": -109.5458, 
        "Marker": 2
    }, 
    "USC00426135": {
        "Lat": 39.7122, 
        "Lon": -111.8319, 
        "Marker": 1
    }, 
    "USC00426357": {
        "Lat": 39.3758, 
        "Lon": -112.3342, 
        "Marker": 2
    }, 
    "USC00426534": {
        "Lat": 37.2722, 
        "Lon": -112.6389, 
        "Marker": 2
    }, 
    "USC00426601": {
        "Lat": 37.8156, 
        "Lon": -112.4386, 
        "Marker": 1
    }, 
    "USC00426869": {
        "Lat": 41.2578, 
        "Lon": -111.8378, 
        "Marker": 2
    }, 
    "USC00426919": {
        "Lat": 40.3675, 
        "Lon": -111.7339, 
        "Marker": 1
    }, 
    "USC00427846": {
        "Lat": 40.6008, 
        "Lon": -111.5842, 
        "Marker": 3
    }, 
    "USC00429111": {
        "Lat": 40.4269, 
        "Lon": -109.5531, 
        "Marker": 2
    }, 
    "USC00429595": {
        "Lat": 41.525, 
        "Lon": -111.1494, 
        "Marker": 1
    }, 
    "USC00429717": {
        "Lat": 37.2092, 
        "Lon": -112.9814, 
        "Marker": 2
    }, 
    "USC00431243": {
        "Lat": 43.3847, 
        "Lon": -72.5989, 
        "Marker": 1
    }, 
    "USC00449186": {
        "Lat": 39.1833, 
        "Lon": -78.1167, 
        "Marker": 1
    }, 
    "USC00450176": {
        "Lat": 48.5119, 
        "Lon": -122.6136, 
        "Marker": 1
    }, 
    "USC00450482": {
        "Lat": 45.7717, 
        "Lon": -122.5286, 
        "Marker": 5
    }, 
    "USC00450668": {
        "Lat": 45.9981, 
        "Lon": -120.3006, 
        "Marker": 4
    }, 
    "USC00450872": {
        "Lat": 47.5689, 
        "Lon": -122.6828, 
        "Marker": 2
    }, 
    "USC00451233": {
        "Lat": 47.4144, 
        "Lon": -121.7561, 
        "Marker": 4
    }, 
    "USC00451350": {
        "Lat": 47.8361, 
        "Lon": -120.0381, 
        "Marker": 5
    }, 
    "USC00451484": {
        "Lat": 48.9672, 
        "Lon": -122.3292, 
        "Marker": 2
    }, 
    "USC00451504": {
        "Lat": 47.1889, 
        "Lon": -120.9131, 
        "Marker": 7
    }, 
    "USC00451679": {
        "Lat": 48.5397, 
        "Lon": -121.7422, 
        "Marker": 2
    }, 
    "USC00451760": {
        "Lat": 46.0625, 
        "Lon": -122.2042, 
        "Marker": 1
    }, 
    "USC00451767": {
        "Lat": 47.9544, 
        "Lon": -118.9997, 
        "Marker": 1
    }, 
    "USC00451783": {
        "Lat": 48.2072, 
        "Lon": -122.6914, 
        "Marker": 1
    }, 
    "USC00451992": {
        "Lat": 48.26, 
        "Lon": -121.6036, 
        "Marker": 3
    }, 
    "USC00452505": {
        "Lat": 46.9692, 
        "Lon": -120.54, 
        "Marker": 3
    }, 
    "USC00452675": {
        "Lat": 47.9753, 
        "Lon": -122.195, 
        "Marker": 4
    }, 
    "USC00452914": {
        "Lat": 47.9558, 
        "Lon": -124.3539, 
        "Marker": 1
    }, 
    "USC00453222": {
        "Lat": 45.8081, 
        "Lon": -120.8428, 
        "Marker": 2
    }, 
    "USC00453529": {
        "Lat": 47.6856, 
        "Lon": -119.1111, 
        "Marker": 3
    }, 
    "USC00453546": {
        "Lat": 46.7225, 
        "Lon": -118.6525, 
        "Marker": 3
    }, 
    "USC00453883": {
        "Lat": 46.2447, 
        "Lon": -118.8786, 
        "Marker": 3
    }, 
    "USC00454154": {
        "Lat": 46.2111, 
        "Lon": -119.1011, 
        "Marker": 3
    }, 
    "USC00454169": {
        "Lat": 47.4172, 
        "Lon": -122.2433, 
        "Marker": 1
    }, 
    "USC00454486": {
        "Lat": 47.3767, 
        "Lon": -121.9614, 
        "Marker": 3
    }, 
    "USC00454572": {
        "Lat": 47.5586, 
        "Lon": -120.675, 
        "Marker": 5
    }, 
    "USC00454679": {
        "Lat": 47.0022, 
        "Lon": -118.5658, 
        "Marker": 1
    }, 
    "USC00455224": {
        "Lat": 47.1358, 
        "Lon": -122.2558, 
        "Marker": 2
    }, 
    "USC00455659": {
        "Lat": 45.9997, 
        "Lon": -121.5403, 
        "Marker": 3
    }, 
    "USC00455688": {
        "Lat": 46.5053, 
        "Lon": -120.1678, 
        "Marker": 6
    }, 
    "USC00455704": {
        "Lat": 47.1414, 
        "Lon": -121.9356, 
        "Marker": 3
    }, 
    "USC00455840": {
        "Lat": 48.6758, 
        "Lon": -121.2419, 
        "Marker": 1
    }, 
    "USC00455946": {
        "Lat": 48.8742, 
        "Lon": -117.8667, 
        "Marker": 2
    }, 
    "USC00456039": {
        "Lat": 47.3328, 
        "Lon": -118.6944, 
        "Marker": 5
    }, 
    "USC00456262": {
        "Lat": 46.6092, 
        "Lon": -121.6744, 
        "Marker": 3
    }, 
    "USC00456295": {
        "Lat": 47.3058, 
        "Lon": -121.8514, 
        "Marker": 4
    }, 
    "USC00456534": {
        "Lat": 47.785, 
        "Lon": -120.6456, 
        "Marker": 3
    }, 
    "USC00456747": {
        "Lat": 46.6461, 
        "Lon": -119.9061, 
        "Marker": 3
    }, 
    "USC00456768": {
        "Lat": 46.2014, 
        "Lon": -119.7581, 
        "Marker": 1
    }, 
    "USC00456789": {
        "Lat": 46.7603, 
        "Lon": -117.1861, 
        "Marker": 1
    }, 
    "USC00456846": {
        "Lat": 47.8092, 
        "Lon": -122.9136, 
        "Marker": 7
    }, 
    "USC00456880": {
        "Lat": 47.2236, 
        "Lon": -119.8525, 
        "Marker": 3
    }, 
    "USC00456898": {
        "Lat": 46.7858, 
        "Lon": -121.7425, 
        "Marker": 5
    }, 
    "USC00456974": {
        "Lat": 48.6469, 
        "Lon": -118.7314, 
        "Marker": 1
    }, 
    "USC00457015": {
        "Lat": 46.3119, 
        "Lon": -119.2633, 
        "Marker": 5
    }, 
    "USC00457059": {
        "Lat": 47.1178, 
        "Lon": -118.3722, 
        "Marker": 2
    }, 
    "USC00457180": {
        "Lat": 47.2325, 
        "Lon": -117.3625, 
        "Marker": 1
    }, 
    "USC00457507": {
        "Lat": 48.4958, 
        "Lon": -122.2355, 
        "Marker": 2
    }, 
    "USC00458034": {
        "Lat": 47.8664, 
        "Lon": -121.7175, 
        "Marker": 7
    }, 
    "USC00458207": {
        "Lat": 46.3236, 
        "Lon": -120.0103, 
        "Marker": 5
    }, 
    "USC00458959": {
        "Lat": 46.4353, 
        "Lon": -120.4203, 
        "Marker": 3
    }, 
    "USC00459012": {
        "Lat": 47.6497, 
        "Lon": -120.08, 
        "Marker": 2
    }, 
    "USC00459074": {
        "Lat": 47.4289, 
        "Lon": -120.31, 
        "Marker": 7
    }, 
    "USC00459238": {
        "Lat": 47.7681, 
        "Lon": -118.7239, 
        "Marker": 2
    }, 
    "USC00459376": {
        "Lat": 48.4742, 
        "Lon": -120.1886, 
        "Marker": 1
    }, 
    "USC00461220": {
        "Lat": 38.9803, 
        "Lon": -80.22, 
        "Marker": 1
    }, 
    "USC00465224": {
        "Lat": 37.8564, 
        "Lon": -80.4042, 
        "Marker": 1
    }, 
    "USC00468384": {
        "Lat": 38.8008, 
        "Lon": -81.3583, 
        "Marker": 1
    }, 
    "USC00469281": {
        "Lat": 39.1139, 
        "Lon": -78.5811, 
        "Marker": 1
    }, 
    "USC00469522": {
        "Lat": 37.7889, 
        "Lon": -80.3083, 
        "Marker": 1
    }, 
    "USC00480140": {
        "Lat": 43.7728, 
        "Lon": -111.0339, 
        "Marker": 1
    }, 
    "USC00480540": {
        "Lat": 44.38, 
        "Lon": -108.035, 
        "Marker": 1
    }, 
    "USC00481000": {
        "Lat": 43.4053, 
        "Lon": -108.1633, 
        "Marker": 1
    }, 
    "USC00482415": {
        "Lat": 44.8919, 
        "Lon": -108.5931, 
        "Marker": 1
    }, 
    "USC00483031": {
        "Lat": 44.4972, 
        "Lon": -108.3906, 
        "Marker": 1
    }, 
    "USC00485105": {
        "Lat": 41.8172, 
        "Lon": -110.5328, 
        "Marker": 1
    }, 
    "USC00488315": {
        "Lat": 44.1333, 
        "Lon": -110.6658, 
        "Marker": 1
    }, 
    "USC00500363": {
        "Lat": 58.3183, 
        "Lon": -134.1003, 
        "Marker": 8
    }, 
    "USC00500657": {
        "Lat": 55.38, 
        "Lon": -131.4683, 
        "Marker": 2
    }, 
    "USC00501987": {
        "Lat": 65.4939, 
        "Lon": -144.6422, 
        "Marker": 1
    }, 
    "USC00502173": {
        "Lat": 60.5561, 
        "Lon": -145.7531, 
        "Marker": 4
    }, 
    "USC00504812": {
        "Lat": 58.1914, 
        "Lon": -152.3722, 
        "Marker": 3
    }, 
    "USC00505519": {
        "Lat": 56.3831, 
        "Lon": -134.6497, 
        "Marker": 3
    }, 
    "USC00505733": {
        "Lat": 61.5664, 
        "Lon": -149.2542, 
        "Marker": 1
    }, 
    "USC00505778": {
        "Lat": 63.7175, 
        "Lon": -148.9692, 
        "Marker": 3
    }, 
    "USC00506870": {
        "Lat": 61.5889, 
        "Lon": -149.0992, 
        "Marker": 1
    }, 
    "USC00507783": {
        "Lat": 62.0911, 
        "Lon": -152.735, 
        "Marker": 2
    }, 
    "USC00517150": {
        "Lat": 21.5739, 
        "Lon": -158.0378, 
        "Marker": 1
    }, 
    "USC00517166": {
        "Lat": 19.2706, 
        "Lon": -155.8747, 
        "Marker": 3
    }, 
    "USW00003103": {
        "Lat": 35.1442, 
        "Lon": -111.6664, 
        "Marker": 1
    }, 
    "USW00003164": {
        "Lat": 32.6233, 
        "Lon": -116.4728, 
        "Marker": 1
    }, 
    "USW00003811": {
        "Lat": 35.5931, 
        "Lon": -88.9167, 
        "Marker": 1
    }, 
    "USW00003904": {
        "Lat": 30.5892, 
        "Lon": -96.3647, 
        "Marker": 1
    }, 
    "USW00003959": {
        "Lat": 36.7683, 
        "Lon": -96.0261, 
        "Marker": 1
    }, 
    "USW00012835": {
        "Lat": 26.585, 
        "Lon": -81.8614, 
        "Marker": 2
    }, 
    "USW00012839": {
        "Lat": 25.7906, 
        "Lon": -80.3164, 
        "Marker": 1
    }, 
    "USW00012912": {
        "Lat": 28.8614, 
        "Lon": -96.9303, 
        "Marker": 2
    }, 
    "USW00012921": {
        "Lat": 29.5442, 
        "Lon": -98.4839, 
        "Marker": 2
    }, 
    "USW00012935": {
        "Lat": 28.7247, 
        "Lon": -96.2536, 
        "Marker": 2
    }, 
    "USW00012947": {
        "Lat": 28.4567, 
        "Lon": -99.2183, 
        "Marker": 1
    }, 
    "USW00013721": {
        "Lat": 38.3, 
        "Lon": -76.4167, 
        "Marker": 1
    }, 
    "USW00013957": {
        "Lat": 32.4506, 
        "Lon": -93.8411, 
        "Marker": 3
    }, 
    "USW00013958": {
        "Lat": 30.3208, 
        "Lon": -97.7603, 
        "Marker": 6
    }, 
    "USW00013960": {
        "Lat": 32.8519, 
        "Lon": -96.8556, 
        "Marker": 3
    }, 
    "USW00013962": {
        "Lat": 32.4106, 
        "Lon": -99.6822, 
        "Marker": 1
    }, 
    "USW00013966": {
        "Lat": 33.9786, 
        "Lon": -98.4928, 
        "Marker": 2
    }, 
    "USW00013970": {
        "Lat": 30.5372, 
        "Lon": -91.1469, 
        "Marker": 1
    }, 
    "USW00013975": {
        "Lat": 36.2967, 
        "Lon": -99.7689, 
        "Marker": 3
    }, 
    "USW00013977": {
        "Lat": 33.4536, 
        "Lon": -94.0075, 
        "Marker": 3
    }, 
    "USW00013978": {
        "Lat": 33.4964, 
        "Lon": -90.0867, 
        "Marker": 2
    }, 
    "USW00013980": {
        "Lat": 37.155, 
        "Lon": -98.0283, 
        "Marker": 3
    }, 
    "USW00013985": {
        "Lat": 37.7608, 
        "Lon": -99.9683, 
        "Marker": 2
    }, 
    "USW00013987": {
        "Lat": 37.1467, 
        "Lon": -94.5022, 
        "Marker": 1
    }, 
    "USW00014605": {
        "Lat": 44.3206, 
        "Lon": -69.7972, 
        "Marker": 1
    }, 
    "USW00014736": {
        "Lat": 40.2964, 
        "Lon": -78.3203, 
        "Marker": 1
    }, 
    "USW00014756": {
        "Lat": 41.2531, 
        "Lon": -70.0608, 
        "Marker": 3
    }, 
    "USW00014765": {
        "Lat": 41.7219, 
        "Lon": -71.4325, 
        "Marker": 1
    }, 
    "USW00014778": {
        "Lat": 41.2433, 
        "Lon": -76.9217, 
        "Marker": 1
    }, 
    "USW00021504": {
        "Lat": 19.7192, 
        "Lon": -155.0531, 
        "Marker": 1
    }, 
    "USW00022534": {
        "Lat": 21.1544, 
        "Lon": -157.0961, 
        "Marker": 2
    }, 
    "USW00022536": {
        "Lat": 21.9839, 
        "Lon": -159.3405, 
        "Marker": 1
    }, 
    "USW00023023": {
        "Lat": 31.9433, 
        "Lon": -102.1889, 
        "Marker": 1
    }, 
    "USW00023041": {
        "Lat": 32.2442, 
        "Lon": -101.4536, 
        "Marker": 2
    }, 
    "USW00023042": {
        "Lat": 33.6542, 
        "Lon": -101.8136, 
        "Marker": 2
    }, 
    "USW00023050": {
        "Lat": 35.0419, 
        "Lon": -106.6156, 
        "Marker": 4
    }, 
    "USW00023051": {
        "Lat": 36.4486, 
        "Lon": -103.1539, 
        "Marker": 1
    }, 
    "USW00023054": {
        "Lat": 35.6542, 
        "Lon": -105.1419, 
        "Marker": 1
    }, 
    "USW00023061": {
        "Lat": 37.4389, 
        "Lon": -105.8614, 
        "Marker": 3
    }, 
    "USW00023062": {
        "Lat": 39.7633, 
        "Lon": -104.8694, 
        "Marker": 2
    }, 
    "USW00023063": {
        "Lat": 39.65, 
        "Lon": -106.9167, 
        "Marker": 2
    }, 
    "USW00023064": {
        "Lat": 37.9272, 
        "Lon": -100.7247, 
        "Marker": 3
    }, 
    "USW00023066": {
        "Lat": 39.1342, 
        "Lon": -108.54, 
        "Marker": 2
    }, 
    "USW00023067": {
        "Lat": 38.0494, 
        "Lon": -103.5122, 
        "Marker": 2
    }, 
    "USW00023070": {
        "Lat": 37.2622, 
        "Lon": -104.3378, 
        "Marker": 1
    }, 
    "USW00023072": {
        "Lat": 34.9325, 
        "Lon": -100.8903, 
        "Marker": 2
    }, 
    "USW00023129": {
        "Lat": 33.8117, 
        "Lon": -118.1464, 
        "Marker": 2
    }, 
    "USW00023153": {
        "Lat": 38.0511, 
        "Lon": -117.0903, 
        "Marker": 1
    }, 
    "USW00023157": {
        "Lat": 37.3711, 
        "Lon": -118.3581, 
        "Marker": 1
    }, 
    "USW00023161": {
        "Lat": 34.8536, 
        "Lon": -116.7858, 
        "Marker": 3
    }, 
    "USW00023184": {
        "Lat": 34.6517, 
        "Lon": -112.4208, 
        "Marker": 2
    }, 
    "USW00023185": {
        "Lat": 39.4839, 
        "Lon": -119.7711, 
        "Marker": 1
    }, 
    "USW00023188": {
        "Lat": 32.7336, 
        "Lon": -117.1831, 
        "Marker": 1
    }, 
    "USW00023190": {
        "Lat": 34.4258, 
        "Lon": -119.8425, 
        "Marker": 2
    }, 
    "USW00023194": {
        "Lat": 35.0281, 
        "Lon": -110.7208, 
        "Marker": 6
    }, 
    "USW00023244": {
        "Lat": 37.4058, 
        "Lon": -122.0481, 
        "Marker": 1
    }, 
    "USW00024029": {
        "Lat": 44.7694, 
        "Lon": -106.9689, 
        "Marker": 1
    }, 
    "USW00024128": {
        "Lat": 40.9017, 
        "Lon": -117.8081, 
        "Marker": 4
    }, 
    "USW00024130": {
        "Lat": 44.8428, 
        "Lon": -117.8086, 
        "Marker": 4
    }, 
    "USW00024131": {
        "Lat": 43.5667, 
        "Lon": -116.2406, 
        "Marker": 1
    }, 
    "USW00024132": {
        "Lat": 45.7881, 
        "Lon": -111.1608, 
        "Marker": 1
    }, 
    "USW00024133": {
        "Lat": 42.5417, 
        "Lon": -113.7661, 
        "Marker": 2
    }, 
    "USW00024138": {
        "Lat": 45.2575, 
        "Lon": -112.5545, 
        "Marker": 1
    }, 
    "USW00024141": {
        "Lat": 47.3078, 
        "Lon": -119.5153, 
        "Marker": 4
    }, 
    "USW00024143": {
        "Lat": 47.4733, 
        "Lon": -111.3822, 
        "Marker": 1
    }, 
    "USW00024149": {
        "Lat": 46.3747, 
        "Lon": -117.0156, 
        "Marker": 2
    }, 
    "USW00024151": {
        "Lat": 42.1492, 
        "Lon": -112.2872, 
        "Marker": 1
    }, 
    "USW00024152": {
        "Lat": 45.5114, 
        "Lon": -118.4247, 
        "Marker": 4
    }, 
    "USW00024153": {
        "Lat": 46.9208, 
        "Lon": -114.0925, 
        "Marker": 1
    }, 
    "USW00024155": {
        "Lat": 45.6906, 
        "Lon": -118.8528, 
        "Marker": 5
    }, 
    "USW00024156": {
        "Lat": 42.9203, 
        "Lon": -112.5711, 
        "Marker": 1
    }, 
    "USW00024157": {
        "Lat": 47.6217, 
        "Lon": -117.5281, 
        "Marker": 1
    }, 
    "USW00024159": {
        "Lat": 47.1928, 
        "Lon": -114.8903, 
        "Marker": 1
    }, 
    "USW00024160": {
        "Lat": 46.0947, 
        "Lon": -118.2869, 
        "Marker": 3
    }, 
    "USW00024172": {
        "Lat": 40.0681, 
        "Lon": -118.5692, 
        "Marker": 4
    }, 
    "USW00024216": {
        "Lat": 40.1519, 
        "Lon": -122.2536, 
        "Marker": 1
    }, 
    "USW00024217": {
        "Lat": 48.7939, 
        "Lon": -122.5372, 
        "Marker": 2
    }, 
    "USW00024219": {
        "Lat": 45.6194, 
        "Lon": -121.1661, 
        "Marker": 5
    }, 
    "USW00024221": {
        "Lat": 44.1278, 
        "Lon": -123.2206, 
        "Marker": 2
    }, 
    "USW00024227": {
        "Lat": 46.9733, 
        "Lon": -122.9033, 
        "Marker": 1
    }, 
    "USW00024229": {
        "Lat": 45.5908, 
        "Lon": -122.6003, 
        "Marker": 2
    }, 
    "USW00024230": {
        "Lat": 44.2558, 
        "Lon": -121.1392, 
        "Marker": 2
    }, 
    "USW00024232": {
        "Lat": 44.905, 
        "Lon": -123.0011, 
        "Marker": 1
    }, 
    "USW00024233": {
        "Lat": 47.4444, 
        "Lon": -122.3139, 
        "Marker": 1
    }, 
    "USW00024235": {
        "Lat": 42.6003, 
        "Lon": -123.3642, 
        "Marker": 4
    }, 
    "USW00024237": {
        "Lat": 47.2767, 
        "Lon": -121.3372, 
        "Marker": 5
    }, 
    "USW00024243": {
        "Lat": 46.5683, 
        "Lon": -120.5428, 
        "Marker": 5
    }, 
    "USW00024255": {
        "Lat": 48.35, 
        "Lon": -122.6667, 
        "Marker": 1
    }, 
    "USW00024284": {
        "Lat": 43.4133, 
        "Lon": -124.2436, 
        "Marker": 1
    }, 
    "USW00025308": {
        "Lat": 55.0389, 
        "Lon": -131.5786, 
        "Marker": 2
    }, 
    "USW00025309": {
        "Lat": 58.3567, 
        "Lon": -134.5639, 
        "Marker": 1
    }, 
    "USW00025325": {
        "Lat": 55.3567, 
        "Lon": -131.7117, 
        "Marker": 2
    }, 
    "USW00025329": {
        "Lat": 56.8056, 
        "Lon": -132.9372, 
        "Marker": 1
    }, 
    "USW00025333": {
        "Lat": 57.0481, 
        "Lon": -135.3647, 
        "Marker": 2
    }, 
    "USW00025339": {
        "Lat": 59.5119, 
        "Lon": -139.6711, 
        "Marker": 2
    }, 
    "USW00025501": {
        "Lat": 57.7511, 
        "Lon": -152.4856, 
        "Marker": 1
    }, 
    "USW00025503": {
        "Lat": 58.6794, 
        "Lon": -156.6294, 
        "Marker": 1
    }, 
    "USW00025507": {
        "Lat": 59.6419, 
        "Lon": -151.4908, 
        "Marker": 1
    }, 
    "USW00025624": {
        "Lat": 55.2208, 
        "Lon": -162.7325, 
        "Marker": 2
    }, 
    "USW00026410": {
        "Lat": 60.4889, 
        "Lon": -145.4511, 
        "Marker": 8
    }, 
    "USW00026412": {
        "Lat": 62.9614, 
        "Lon": -141.9292, 
        "Marker": 2
    }, 
    "USW00026425": {
        "Lat": 62.1592, 
        "Lon": -145.4589, 
        "Marker": 3
    }, 
    "USW00026435": {
        "Lat": 64.55, 
        "Lon": -149.0717, 
        "Marker": 1
    }, 
    "USW00026438": {
        "Lat": 60.1283, 
        "Lon": -149.4167, 
        "Marker": 2
    }, 
    "USW00026451": {
        "Lat": 61.1689, 
        "Lon": -150.0278, 
        "Marker": 1
    }, 
    "USW00026510": {
        "Lat": 62.9575, 
        "Lon": -155.6103, 
        "Marker": 2
    }, 
    "USW00026514": {
        "Lat": 61.9772, 
        "Lon": -151.2169, 
        "Marker": 1
    }, 
    "USW00026528": {
        "Lat": 62.32, 
        "Lon": -150.095, 
        "Marker": 2
    }, 
    "USW00026616": {
        "Lat": 66.8667, 
        "Lon": -162.6333, 
        "Marker": 2
    }, 
    "USW00092811": {
        "Lat": 25.8064, 
        "Lon": -80.1336, 
        "Marker": 2
    }, 
    "USW00093010": {
        "Lat": 39.1894, 
        "Lon": -103.7158, 
        "Marker": 1
    }, 
    "USW00093026": {
        "Lat": 31.4583, 
        "Lon": -109.6061, 
        "Marker": 2
    }, 
    "USW00093033": {
        "Lat": 32.3336, 
        "Lon": -104.2581, 
        "Marker": 1
    }, 
    "USW00093037": {
        "Lat": 38.81, 
        "Lon": -104.6883, 
        "Marker": 1
    }, 
    "USW00093042": {
        "Lat": 36.0167, 
        "Lon": -102.55, 
        "Marker": 1
    }, 
    "USW00093045": {
        "Lat": 33.2367, 
        "Lon": -107.2681, 
        "Marker": 1
    }, 
    "USW00093057": {
        "Lat": 35.1664, 
        "Lon": -107.8992, 
        "Marker": 1
    }, 
    "USW00093058": {
        "Lat": 38.29, 
        "Lon": -104.4983, 
        "Marker": 2
    }, 
    "USW00093102": {
        "Lat": 39.4167, 
        "Lon": -118.7167, 
        "Marker": 3
    }, 
    "USW00093112": {
        "Lat": 32.7, 
        "Lon": -117.2, 
        "Marker": 1
    }, 
    "USW00093139": {
        "Lat": 34.2325, 
        "Lon": -111.3447, 
        "Marker": 3
    }, 
    "USW00093801": {
        "Lat": 34.3478, 
        "Lon": -85.1611, 
        "Marker": 1
    }, 
    "USW00093806": {
        "Lat": 33.2119, 
        "Lon": -87.6161, 
        "Marker": 1
    }, 
    "USW00093812": {
        "Lat": 39.1033, 
        "Lon": -84.4189, 
        "Marker": 1
    }, 
    "USW00093814": {
        "Lat": 39.0431, 
        "Lon": -84.6717, 
        "Marker": 1
    }, 
    "USW00093914": {
        "Lat": 31.7831, 
        "Lon": -95.6039, 
        "Marker": 5
    }, 
    "USW00093985": {
        "Lat": 32.7817, 
        "Lon": -98.0603, 
        "Marker": 2
    }, 
    "USW00093986": {
        "Lat": 34.9894, 
        "Lon": -99.0525, 
        "Marker": 1
    }, 
    "USW00093987": {
        "Lat": 31.2361, 
        "Lon": -94.7544, 
        "Marker": 2
    }, 
    "USW00093988": {
        "Lat": 34.175, 
        "Lon": -91.9347, 
        "Marker": 1
    }, 
    "USW00093992": {
        "Lat": 33.2208, 
        "Lon": -92.8142, 
        "Marker": 1
    }, 
    "USW00094224": {
        "Lat": 46.1569, 
        "Lon": -123.8825, 
        "Marker": 1
    }, 
    "USW00094239": {
        "Lat": 47.3978, 
        "Lon": -120.2014, 
        "Marker": 2
    }
}