{
    "RQC00660158": {
        "Lat": 18.1281, 
        "Lon": -66.2642, 
        "Marker": 11
    }, 
    "RQC00662801": {
        "Lat": 18.3808, 
        "Lon": -67.1569, 
        "Marker": 1
    }, 
    "RQC00663431": {
        "Lat": 18.3361, 
        "Lon": -66.6667, 
        "Marker": 3
    }, 
    "RQC00664276": {
        "Lat": 18.2583, 
        "Lon": -65.9922, 
        "Marker": 2
    }, 
    "RQC00664702": {
        "Lat": 18.4653, 
        "Lon": -67.0525, 
        "Marker": 2
    }, 
    "RQC00665064": {
        "Lat": 18.2264, 
        "Lon": -65.9114, 
        "Marker": 3
    }, 
    "RQC00665097": {
        "Lat": 18.0331, 
        "Lon": -67.0722, 
        "Marker": 2
    }, 
    "RQC00665807": {
        "Lat": 18.4308, 
        "Lon": -66.4661, 
        "Marker": 1
    }, 
    "RQC00668306": {
        "Lat": 18.3906, 
        "Lon": -66.0542, 
        "Marker": 1
    }, 
    "RQW00011603": {
        "Lat": 18.4981, 
        "Lon": -67.1294, 
        "Marker": 2
    }, 
    "RQW00011641": {
        "Lat": 18.4325, 
        "Lon": -66.0108, 
        "Marker": 1
    }, 
    "USC00020060": {
        "Lat": 33.9433, 
        "Lon": -113.1875, 
        "Marker": 1
    }, 
    "USC00020586": {
        "Lat": 34.5972, 
        "Lon": -113.1739, 
        "Marker": 1
    }, 
    "USC00020808": {
        "Lat": 33.4783, 
        "Lon": -109.7517, 
        "Marker": 2
    }, 
    "USC00021001": {
        "Lat": 36.2147, 
        "Lon": -112.062, 
        "Marker": 1
    }, 
    "USC00021314": {
        "Lat": 32.9947, 
        "Lon": -111.5367, 
        "Marker": 1
    }, 
    "USC00021654": {
        "Lat": 34.7569, 
        "Lon": -112.4567, 
        "Marker": 1
    }, 
    "USC00022109": {
        "Lat": 34.305, 
        "Lon": -112.165, 
        "Marker": 1
    }, 
    "USC00024977": {
        "Lat": 33.4992, 
        "Lon": -112.3631, 
        "Marker": 1
    }, 
    "USC00025412": {
        "Lat": 34.1142, 
        "Lon": -109.8589, 
        "Marker": 2
    }, 
    "USC00025924": {
        "Lat": 31.4553, 
        "Lon": -110.9681, 
        "Marker": 1
    }, 
    "USC00026132": {
        "Lat": 31.9556, 
        "Lon": -112.8003, 
        "Marker": 2
    }, 
    "USC00028865": {
        "Lat": 31.5678, 
        "Lon": -111.0497, 
        "Marker": 2
    }, 
    "USC00029334": {
        "Lat": 32.2553, 
        "Lon": -109.8369, 
        "Marker": 2
    }, 
    "USC00040212": {
        "Lat": 38.5731, 
        "Lon": -122.4406, 
        "Marker": 2
    }, 
    "USC00040343": {
        "Lat": 36.4914, 
        "Lon": -118.8253, 
        "Marker": 1
    }, 
    "USC00041253": {
        "Lat": 34.5822, 
        "Lon": -119.9817, 
        "Marker": 1
    }, 
    "USC00041758": {
        "Lat": 32.64, 
        "Lon": -117.0858, 
        "Marker": 1
    }, 
    "USC00042081": {
        "Lat": 39.8158, 
        "Lon": -123.2444, 
        "Marker": 1
    }, 
    "USC00042239": {
        "Lat": 32.9897, 
        "Lon": -116.5872, 
        "Marker": 2
    }, 
    "USC00043855": {
        "Lat": 33.7044, 
        "Lon": -115.6289, 
        "Marker": 2
    }, 
    "USC00044211": {
        "Lat": 33.7572, 
        "Lon": -116.7067, 
        "Marker": 1
    }, 
    "USC00045311": {
        "Lat": 40.5411, 
        "Lon": -121.5767, 
        "Marker": 2
    }, 
    "USC00045449": {
        "Lat": 41.2514, 
        "Lon": -122.1383, 
        "Marker": 1
    }, 
    "USC00045866": {
        "Lat": 35.3672, 
        "Lon": -120.8456, 
        "Marker": 1
    }, 
    "USC00045915": {
        "Lat": 37.8792, 
        "Lon": -121.9303, 
        "Marker": 1
    }, 
    "USC00045933": {
        "Lat": 37.3436, 
        "Lon": -121.6425, 
        "Marker": 2
    }, 
    "USC00046136": {
        "Lat": 39.2467, 
        "Lon": -121.0008, 
        "Marker": 2
    }, 
    "USC00046175": {
        "Lat": 33.6025, 
        "Lon": -117.8803, 
        "Marker": 1
    }, 
    "USC00046377": {
        "Lat": 33.2097, 
        "Lon": -117.395, 
        "Marker": 1
    }, 
    "USC00046943": {
        "Lat": 35.1597, 
        "Lon": -120.6831, 
        "Marker": 1
    }, 
    "USC00046962": {
        "Lat": 38.7333, 
        "Lon": -120.7333, 
        "Marker": 2
    }, 
    "USC00047916": {
        "Lat": 36.9906, 
        "Lon": -121.9911, 
        "Marker": 1
    }, 
    "USC00048135": {
        "Lat": 40.7142, 
        "Lon": -122.4161, 
        "Marker": 3
    }, 
    "USC00048380": {
        "Lat": 37.5072, 
        "Lon": -119.6331, 
        "Marker": 2
    }, 
    "USC00048606": {
        "Lat": 39.5631, 
        "Lon": -121.1078, 
        "Marker": 1
    }, 
    "USC00049152": {
        "Lat": 34.0697, 
        "Lon": -118.4428, 
        "Marker": 1
    }, 
    "USC00049785": {
        "Lat": 34.1819, 
        "Lon": -118.5744, 
        "Marker": 1
    }, 
    "USC00054770": {
        "Lat": 38.0936, 
        "Lon": -102.6306, 
        "Marker": 1
    }, 
    "USC00056832": {
        "Lat": 40.0894, 
        "Lon": -108.7717, 
        "Marker": 5
    }, 
    "USC00057936": {
        "Lat": 40.4883, 
        "Lon": -106.8233, 
        "Marker": 2
    }, 
    "USC00058184": {
        "Lat": 38.8183, 
        "Lon": -106.6086, 
        "Marker": 1
    }, 
    "USC00083163": {
        "Lat": 26.1019, 
        "Lon": -80.2011, 
        "Marker": 1
    }, 
    "USC00101363": {
        "Lat": 48.0864, 
        "Lon": -116.0572, 
        "Marker": 1
    }, 
    "USC00101671": {
        "Lat": 43.9772, 
        "Lon": -113.8289, 
        "Marker": 4
    }, 
    "USC00102260": {
        "Lat": 43.465, 
        "Lon": -113.5581, 
        "Marker": 4
    }, 
    "USC00103143": {
        "Lat": 46.0931, 
        "Lon": -115.5356, 
        "Marker": 1
    }, 
    "USC00103882": {
        "Lat": 43.7186, 
        "Lon": -113.5472, 
        "Marker": 1
    }, 
    "USC00103964": {
        "Lat": 43.9664, 
        "Lon": -112.2642, 
        "Marker": 1
    }, 
    "USC00104442": {
        "Lat": 43.8383, 
        "Lon": -115.8319, 
        "Marker": 3
    }, 
    "USC00106152": {
        "Lat": 46.7281, 
        "Lon": -116.9558, 
        "Marker": 1
    }, 
    "USC00106424": {
        "Lat": 46.2325, 
        "Lon": -116.243, 
        "Marker": 1
    }, 
    "USC00106542": {
        "Lat": 42.2342, 
        "Lon": -113.8981, 
        "Marker": 1
    }, 
    "USC00107301": {
        "Lat": 46.9603, 
        "Lon": -116.855, 
        "Marker": 1
    }, 
    "USC00107386": {
        "Lat": 48.3511, 
        "Lon": -116.8353, 
        "Marker": 1
    }, 
    "USC00242409": {
        "Lat": 45.2128, 
        "Lon": -112.6447, 
        "Marker": 1
    }, 
    "USC00243489": {
        "Lat": 47.6017, 
        "Lon": -112.7536, 
        "Marker": 1
    }, 
    "USC00243984": {
        "Lat": 47.3889, 
        "Lon": -115.4225, 
        "Marker": 1
    }, 
    "USC00244328": {
        "Lat": 48.3425, 
        "Lon": -114.0217, 
        "Marker": 1
    }, 
    "USC00245020": {
        "Lat": 47.9733, 
        "Lon": -115.2239, 
        "Marker": 1
    }, 
    "USC00245043": {
        "Lat": 47.4083, 
        "Lon": -113.7125, 
        "Marker": 1
    }, 
    "USC00246472": {
        "Lat": 46.3158, 
        "Lon": -113.3, 
        "Marker": 1
    }, 
    "USC00246640": {
        "Lat": 47.6775, 
        "Lon": -114.2419, 
        "Marker": 1
    }, 
    "USC00247448": {
        "Lat": 47.2142, 
        "Lon": -113.5203, 
        "Marker": 1
    }, 
    "USC00249023": {
        "Lat": 46.0289, 
        "Lon": -110.51, 
        "Marker": 1
    }, 
    "USC00267175": {
        "Lat": 39.2764, 
        "Lon": -114.9911, 
        "Marker": 1
    }, 
    "USC00267369": {
        "Lat": 35.4661, 
        "Lon": -114.9217, 
        "Marker": 3
    }, 
    "USC00291138": {
        "Lat": 33.8044, 
        "Lon": -106.8908, 
        "Marker": 1
    }, 
    "USC00291630": {
        "Lat": 36.7408, 
        "Lon": -105.5956, 
        "Marker": 1
    }, 
    "USC00292510": {
        "Lat": 35.1842, 
        "Lon": -105.0569, 
        "Marker": 3
    }, 
    "USC00293775": {
        "Lat": 31.9175, 
        "Lon": -108.3247, 
        "Marker": 1
    }, 
    "USC00295150": {
        "Lat": 34.7675, 
        "Lon": -106.7611, 
        "Marker": 1
    }, 
    "USC00297340": {
        "Lat": 32.7047, 
        "Lon": -108.7281, 
        "Marker": 2
    }, 
    "USC00297386": {
        "Lat": 33.7158, 
        "Lon": -108.7769, 
        "Marker": 2
    }, 
    "USC00299820": {
        "Lat": 35.9478, 
        "Lon": -106.7469, 
        "Marker": 1
    }, 
    "USC00321435": {
        "Lat": 48.8628, 
        "Lon": -97.7014, 
        "Marker": 1
    }, 
    "USC00325660": {
        "Lat": 47.4989, 
        "Lon": -97.3514, 
        "Marker": 1
    }, 
    "USC00350471": {
        "Lat": 43.1497, 
        "Lon": -124.4019, 
        "Marker": 1
    }, 
    "USC00350694": {
        "Lat": 44.0569, 
        "Lon": -121.285, 
        "Marker": 2
    }, 
    "USC00351643": {
        "Lat": 46.1081, 
        "Lon": -123.2058, 
        "Marker": 1
    }, 
    "USC00351862": {
        "Lat": 44.6342, 
        "Lon": -123.19, 
        "Marker": 1
    }, 
    "USC00351902": {
        "Lat": 43.7178, 
        "Lon": -123.0578, 
        "Marker": 1
    }, 
    "USC00351946": {
        "Lat": 42.8967, 
        "Lon": -122.1328, 
        "Marker": 1
    }, 
    "USC00352112": {
        "Lat": 44.9464, 
        "Lon": -123.2911, 
        "Marker": 2
    }, 
    "USC00352440": {
        "Lat": 45.4539, 
        "Lon": -121.1303, 
        "Marker": 1
    }, 
    "USC00352867": {
        "Lat": 44.0494, 
        "Lon": -123.3703, 
        "Marker": 1
    }, 
    "USC00352997": {
        "Lat": 45.5247, 
        "Lon": -123.1025, 
        "Marker": 1
    }, 
    "USC00353402": {
        "Lat": 45.3014, 
        "Lon": -121.7417, 
        "Marker": 1
    }, 
    "USC00353770": {
        "Lat": 45.4486, 
        "Lon": -122.1547, 
        "Marker": 2
    }, 
    "USC00353827": {
        "Lat": 45.3653, 
        "Lon": -119.5639, 
        "Marker": 1
    }, 
    "USC00354811": {
        "Lat": 44.1014, 
        "Lon": -122.6886, 
        "Marker": 2
    }, 
    "USC00355734": {
        "Lat": 45.4825, 
        "Lon": -120.7236, 
        "Marker": 1
    }, 
    "USC00356213": {
        "Lat": 43.7428, 
        "Lon": -122.4433, 
        "Marker": 5
    }, 
    "USC00356334": {
        "Lat": 45.3558, 
        "Lon": -122.6047, 
        "Marker": 1
    }, 
    "USC00358466": {
        "Lat": 45.1219, 
        "Lon": -122.07, 
        "Marker": 3
    }, 
    "USC00358494": {
        "Lat": 45.4539, 
        "Lon": -123.8519, 
        "Marker": 2
    }, 
    "USC00411048": {
        "Lat": 30.1592, 
        "Lon": -96.3972, 
        "Marker": 1
    }, 
    "USC00417704": {
        "Lat": 28.0286, 
        "Lon": -97.0567, 
        "Marker": 1
    }, 
    "USC00417983": {
        "Lat": 29.8833, 
        "Lon": -97.9494, 
        "Marker": 1
    }, 
    "USC00418415": {
        "Lat": 30.0067, 
        "Lon": -97.1689, 
        "Marker": 1
    }, 
    "USC00421214": {
        "Lat": 39.2078, 
        "Lon": -111.0125, 
        "Marker": 1
    }, 
    "USC00422173": {
        "Lat": 40.4378, 
        "Lon": -109.3045, 
        "Marker": 1
    }, 
    "USC00422578": {
        "Lat": 39.3583, 
        "Lon": -111.5992, 
        "Marker": 1
    }, 
    "USC00422996": {
        "Lat": 40.2842, 
        "Lon": -109.8611, 
        "Marker": 1
    }, 
    "USC00424100": {
        "Lat": 37.3858, 
        "Lon": -109.075, 
        "Marker": 1
    }, 
    "USC00424342": {
        "Lat": 40.3611, 
        "Lon": -109.3464, 
        "Marker": 1
    }, 
    "USC00426123": {
        "Lat": 40.4178, 
        "Lon": -110.0511, 
        "Marker": 1
    }, 
    "USC00426568": {
        "Lat": 40.1342, 
        "Lon": -109.6422, 
        "Marker": 2
    }, 
    "USC00427395": {
        "Lat": 40.2878, 
        "Lon": -109.9586, 
        "Marker": 1
    }, 
    "USC00429595": {
        "Lat": 41.525, 
        "Lon": -111.1494, 
        "Marker": 1
    }, 
    "USC00450176": {
        "Lat": 48.5119, 
        "Lon": -122.6136, 
        "Marker": 1
    }, 
    "USC00451233": {
        "Lat": 47.4144, 
        "Lon": -121.7561, 
        "Marker": 1
    }, 
    "USC00451504": {
        "Lat": 47.1889, 
        "Lon": -120.9131, 
        "Marker": 3
    }, 
    "USC00451666": {
        "Lat": 48.5558, 
        "Lon": -119.7492, 
        "Marker": 1
    }, 
    "USC00451679": {
        "Lat": 48.5397, 
        "Lon": -121.7422, 
        "Marker": 2
    }, 
    "USC00451783": {
        "Lat": 48.2072, 
        "Lon": -122.6914, 
        "Marker": 1
    }, 
    "USC00452157": {
        "Lat": 48.7142, 
        "Lon": -121.1431, 
        "Marker": 2
    }, 
    "USC00452505": {
        "Lat": 46.9692, 
        "Lon": -120.54, 
        "Marker": 1
    }, 
    "USC00452531": {
        "Lat": 47.0092, 
        "Lon": -123.4008, 
        "Marker": 2
    }, 
    "USC00452675": {
        "Lat": 47.9753, 
        "Lon": -122.195, 
        "Marker": 1
    }, 
    "USC00452914": {
        "Lat": 47.9558, 
        "Lon": -124.3539, 
        "Marker": 4
    }, 
    "USC00453320": {
        "Lat": 46.8008, 
        "Lon": -124.0864, 
        "Marker": 4
    }, 
    "USC00454486": {
        "Lat": 47.3767, 
        "Lon": -121.9614, 
        "Marker": 1
    }, 
    "USC00455525": {
        "Lat": 47.8453, 
        "Lon": -121.9944, 
        "Marker": 1
    }, 
    "USC00455688": {
        "Lat": 46.5053, 
        "Lon": -120.1678, 
        "Marker": 1
    }, 
    "USC00455704": {
        "Lat": 47.1414, 
        "Lon": -121.9356, 
        "Marker": 1
    }, 
    "USC00456096": {
        "Lat": 48.6117, 
        "Lon": -122.8064, 
        "Marker": 2
    }, 
    "USC00456262": {
        "Lat": 46.6092, 
        "Lon": -121.6744, 
        "Marker": 1
    }, 
    "USC00456295": {
        "Lat": 47.3058, 
        "Lon": -121.8514, 
        "Marker": 1
    }, 
    "USC00456534": {
        "Lat": 47.785, 
        "Lon": -120.6456, 
        "Marker": 1
    }, 
    "USC00456768": {
        "Lat": 46.2014, 
        "Lon": -119.7581, 
        "Marker": 1
    }, 
    "USC00456789": {
        "Lat": 46.7603, 
        "Lon": -117.1861, 
        "Marker": 1
    }, 
    "USC00456846": {
        "Lat": 47.8092, 
        "Lon": -122.9136, 
        "Marker": 1
    }, 
    "USC00456898": {
        "Lat": 46.7858, 
        "Lon": -121.7425, 
        "Marker": 1
    }, 
    "USC00456974": {
        "Lat": 48.6469, 
        "Lon": -118.7314, 
        "Marker": 1
    }, 
    "USC00457015": {
        "Lat": 46.3119, 
        "Lon": -119.2633, 
        "Marker": 1
    }, 
    "USC00457507": {
        "Lat": 48.4958, 
        "Lon": -122.2355, 
        "Marker": 1
    }, 
    "USC00458034": {
        "Lat": 47.8664, 
        "Lon": -121.7175, 
        "Marker": 1
    }, 
    "USC00458207": {
        "Lat": 46.3236, 
        "Lon": -120.0103, 
        "Marker": 1
    }, 
    "USC00458959": {
        "Lat": 46.4353, 
        "Lon": -120.4203, 
        "Marker": 1
    }, 
    "USC00459012": {
        "Lat": 47.6497, 
        "Lon": -120.08, 
        "Marker": 1
    }, 
    "USC00480865": {
        "Lat": 43.2278, 
        "Lon": -110.4358, 
        "Marker": 3
    }, 
    "USC00485105": {
        "Lat": 41.8172, 
        "Lon": -110.5328, 
        "Marker": 3
    }, 
    "USC00486440": {
        "Lat": 43.8567, 
        "Lon": -110.5889, 
        "Marker": 2
    }, 
    "USC00488315": {
        "Lat": 44.1333, 
        "Lon": -110.6658, 
        "Marker": 1
    }, 
    "USC00500363": {
        "Lat": 58.3183, 
        "Lon": -134.1003, 
        "Marker": 6
    }, 
    "USC00500657": {
        "Lat": 55.38, 
        "Lon": -131.4683, 
        "Marker": 1
    }, 
    "USC00502107": {
        "Lat": 64.8603, 
        "Lon": -147.8483, 
        "Marker": 3
    }, 
    "USC00502607": {
        "Lat": 64.7856, 
        "Lon": -141.2036, 
        "Marker": 1
    }, 
    "USC00504812": {
        "Lat": 58.1914, 
        "Lon": -152.3722, 
        "Marker": 10
    }, 
    "USC00505519": {
        "Lat": 56.3831, 
        "Lon": -134.6497, 
        "Marker": 2
    }, 
    "USC00505644": {
        "Lat": 64.9989, 
        "Lon": -150.638, 
        "Marker": 2
    }, 
    "USC00505733": {
        "Lat": 61.5664, 
        "Lon": -149.2542, 
        "Marker": 3
    }, 
    "USC00505778": {
        "Lat": 63.7175, 
        "Lon": -148.9692, 
        "Marker": 2
    }, 
    "USC00505881": {
        "Lat": 63.9033, 
        "Lon": -152.2817, 
        "Marker": 3
    }, 
    "USC00506870": {
        "Lat": 61.5889, 
        "Lon": -149.0992, 
        "Marker": 4
    }, 
    "USC00509641": {
        "Lat": 64.8569, 
        "Lon": -147.8611, 
        "Marker": 5
    }, 
    "USC00511004": {
        "Lat": 20.7603, 
        "Lon": -156.2469, 
        "Marker": 2
    }, 
    "USC00511125": {
        "Lat": 20.7947, 
        "Lon": -156.0153, 
        "Marker": 1
    }, 
    "USC00512751": {
        "Lat": 19.5336, 
        "Lon": -155.9258, 
        "Marker": 1
    }, 
    "USC00517166": {
        "Lat": 19.2706, 
        "Lon": -155.8747, 
        "Marker": 2
    }, 
    "USW00003103": {
        "Lat": 35.1442, 
        "Lon": -111.6664, 
        "Marker": 1
    }, 
    "USW00003122": {
        "Lat": 33.8017, 
        "Lon": -118.3411, 
        "Marker": 2
    }, 
    "USW00003164": {
        "Lat": 32.6233, 
        "Lon": -116.4728, 
        "Marker": 1
    }, 
    "USW00012926": {
        "Lat": 27.6833, 
        "Lon": -97.2833, 
        "Marker": 2
    }, 
    "USW00012935": {
        "Lat": 28.7247, 
        "Lon": -96.2536, 
        "Marker": 1
    }, 
    "USW00014916": {
        "Lat": 47.9428, 
        "Lon": -97.1839, 
        "Marker": 1
    }, 
    "USW00021504": {
        "Lat": 19.7192, 
        "Lon": -155.0531, 
        "Marker": 5
    }, 
    "USW00022516": {
        "Lat": 20.8997, 
        "Lon": -156.4286, 
        "Marker": 1
    }, 
    "USW00022521": {
        "Lat": 21.3239, 
        "Lon": -157.9294, 
        "Marker": 2
    }, 
    "USW00022534": {
        "Lat": 21.1544, 
        "Lon": -157.0961, 
        "Marker": 11
    }, 
    "USW00023009": {
        "Lat": 33.3075, 
        "Lon": -104.5083, 
        "Marker": 1
    }, 
    "USW00023044": {
        "Lat": 31.8111, 
        "Lon": -106.3758, 
        "Marker": 2
    }, 
    "USW00023063": {
        "Lat": 39.65, 
        "Lon": -106.9167, 
        "Marker": 1
    }, 
    "USW00023129": {
        "Lat": 33.8117, 
        "Lon": -118.1464, 
        "Marker": 4
    }, 
    "USW00023157": {
        "Lat": 37.3711, 
        "Lon": -118.3581, 
        "Marker": 3
    }, 
    "USW00023159": {
        "Lat": 37.7064, 
        "Lon": -112.1456, 
        "Marker": 3
    }, 
    "USW00023160": {
        "Lat": 32.1314, 
        "Lon": -110.9553, 
        "Marker": 1
    }, 
    "USW00023161": {
        "Lat": 34.8536, 
        "Lon": -116.7858, 
        "Marker": 1
    }, 
    "USW00023162": {
        "Lat": 39.3375, 
        "Lon": -112.5858, 
        "Marker": 1
    }, 
    "USW00023169": {
        "Lat": 36.0719, 
        "Lon": -115.1633, 
        "Marker": 2
    }, 
    "USW00023183": {
        "Lat": 33.4278, 
        "Lon": -112.0039, 
        "Marker": 1
    }, 
    "USW00023188": {
        "Lat": 32.7336, 
        "Lon": -117.1831, 
        "Marker": 2
    }, 
    "USW00023225": {
        "Lat": 39.2775, 
        "Lon": -120.7103, 
        "Marker": 1
    }, 
    "USW00023273": {
        "Lat": 34.8994, 
        "Lon": -120.4486, 
        "Marker": 1
    }, 
    "USW00024027": {
        "Lat": 41.5944, 
        "Lon": -109.0528, 
        "Marker": 2
    }, 
    "USW00024138": {
        "Lat": 45.2575, 
        "Lon": -112.5545, 
        "Marker": 1
    }, 
    "USW00024227": {
        "Lat": 46.9733, 
        "Lon": -122.9033, 
        "Marker": 1
    }, 
    "USW00024232": {
        "Lat": 44.905, 
        "Lon": -123.0011, 
        "Marker": 1
    }, 
    "USW00024233": {
        "Lat": 47.4444, 
        "Lon": -122.3139, 
        "Marker": 1
    }, 
    "USW00024235": {
        "Lat": 42.6003, 
        "Lon": -123.3642, 
        "Marker": 2
    }, 
    "USW00024243": {
        "Lat": 46.5683, 
        "Lon": -120.5428, 
        "Marker": 1
    }, 
    "USW00024255": {
        "Lat": 48.35, 
        "Lon": -122.6667, 
        "Marker": 1
    }, 
    "USW00024284": {
        "Lat": 43.4133, 
        "Lon": -124.2436, 
        "Marker": 1
    }, 
    "USW00025308": {
        "Lat": 55.0389, 
        "Lon": -131.5786, 
        "Marker": 1
    }, 
    "USW00025309": {
        "Lat": 58.3567, 
        "Lon": -134.5639, 
        "Marker": 6
    }, 
    "USW00025329": {
        "Lat": 56.8056, 
        "Lon": -132.9372, 
        "Marker": 1
    }, 
    "USW00025333": {
        "Lat": 57.0481, 
        "Lon": -135.3647, 
        "Marker": 1
    }, 
    "USW00025339": {
        "Lat": 59.5119, 
        "Lon": -139.6711, 
        "Marker": 5
    }, 
    "USW00025501": {
        "Lat": 57.7511, 
        "Lon": -152.4856, 
        "Marker": 1
    }, 
    "USW00025503": {
        "Lat": 58.6794, 
        "Lon": -156.6294, 
        "Marker": 3
    }, 
    "USW00025506": {
        "Lat": 59.7494, 
        "Lon": -154.9089, 
        "Marker": 7
    }, 
    "USW00025507": {
        "Lat": 59.6419, 
        "Lon": -151.4908, 
        "Marker": 4
    }, 
    "USW00026410": {
        "Lat": 60.4889, 
        "Lon": -145.4511, 
        "Marker": 8
    }, 
    "USW00026411": {
        "Lat": 64.8039, 
        "Lon": -147.8761, 
        "Marker": 2
    }, 
    "USW00026412": {
        "Lat": 62.9614, 
        "Lon": -141.9292, 
        "Marker": 4
    }, 
    "USW00026415": {
        "Lat": 63.9944, 
        "Lon": -145.7214, 
        "Marker": 1
    }, 
    "USW00026425": {
        "Lat": 62.1592, 
        "Lon": -145.4589, 
        "Marker": 2
    }, 
    "USW00026438": {
        "Lat": 60.1283, 
        "Lon": -149.4167, 
        "Marker": 9
    }, 
    "USW00026442": {
        "Lat": 61.1303, 
        "Lon": -146.3517, 
        "Marker": 5
    }, 
    "USW00026451": {
        "Lat": 61.1689, 
        "Lon": -150.0278, 
        "Marker": 4
    }, 
    "USW00026523": {
        "Lat": 60.5797, 
        "Lon": -151.2392, 
        "Marker": 3
    }, 
    "USW00026528": {
        "Lat": 62.32, 
        "Lon": -150.095, 
        "Marker": 2
    }, 
    "USW00026533": {
        "Lat": 66.9161, 
        "Lon": -151.5089, 
        "Marker": 1
    }, 
    "USW00026615": {
        "Lat": 60.785, 
        "Lon": -161.8292, 
        "Marker": 2
    }, 
    "USW00026616": {
        "Lat": 66.8667, 
        "Lon": -162.6333, 
        "Marker": 1
    }, 
    "USW00026617": {
        "Lat": 64.5111, 
        "Lon": -165.44, 
        "Marker": 7
    }, 
    "USW00093026": {
        "Lat": 31.4583, 
        "Lon": -109.6061, 
        "Marker": 1
    }, 
    "USW00093107": {
        "Lat": 32.8667, 
        "Lon": -117.1333, 
        "Marker": 1
    }, 
    "USW00093111": {
        "Lat": 34.1167, 
        "Lon": -119.1167, 
        "Marker": 1
    }, 
    "USW00093112": {
        "Lat": 32.7, 
        "Lon": -117.2, 
        "Marker": 1
    }, 
    "USW00093115": {
        "Lat": 32.5667, 
        "Lon": -117.1167, 
        "Marker": 1
    }, 
    "USW00093129": {
        "Lat": 37.7086, 
        "Lon": -113.0944, 
        "Marker": 1
    }, 
    "USW00093139": {
        "Lat": 34.2325, 
        "Lon": -111.3447, 
        "Marker": 2
    }, 
    "USW00094225": {
        "Lat": 46.9728, 
        "Lon": -123.9303, 
        "Marker": 1
    }, 
    "VQW00011640": {
        "Lat": 18.3331, 
        "Lon": -64.9667, 
        "Marker": 2
    }
}